design/FSM/controller_FSM.sv
module controller_FSM (
    input                           clk             ,
    input                           rst_n           ,
    input   [3:0]                   input_load_number,//输入input第几排 0-15
    input   [2:0]                   layer_number,//计算第几层0-7
    input   [2:0]                   weight_number,//0-7  
    output                          result_valid_o,                  
    //dataload
    input                           dataload_weight_valid,
    input                           dataload_input_valid,
    input                          dataload_en_i,
    //pe_array
    input                           array_rounder_vaild,
    output                          array_keep,
    output                          array_rounder_en,
    output                          array_input_type//可以在top实现
);
localparam [2:0] // for 8 states
    IDLE = 0,
    FIRST_LAYER_LDDAT1  = 1,//load 2 weight
    FIRST_LAYER_LDDAT2 = 2, //
    FIRST_LAYER_NORMAL= 3,  
    FIRST_LAYER_ROUND = 4, 
    OTHER_LAYER_NORMAL = 5, 
    OTHER_LAYER_ROUND = 6, 
    OUTPUT = 7;

reg[3:0] state_cur, state_next;
always_ff @( posedge clk ) begin
    if (!rst_n) begin
        state_cur <= IDLE;
    end else begin
        state_cur <= state_next;
    end
end

always_comb begin :N_state
    case (state_cur)
        IDLE : state_next = (!rst_n || !dataload_en_i) ?  IDLE : FIRST_LAYER_LDDAT1 ;
        FIRST_LAYER_LDDAT1  :   state_next =    (!rst_n)                ?       IDLE:
                                                (dataload_weight_valid) ?       FIRST_LAYER_LDDAT2  :
                                                FIRST_LAYER_LDDAT1  ;

        FIRST_LAYER_LDDAT2  :    state_next =   (!rst_n)                ?       IDLE:
                                                (dataload_input_valid)  ?       FIRST_LAYER_NORMAL  :
                                                FIRST_LAYER_LDDAT2  ;                      

        FIRST_LAYER_NORMAL  :    state_next =   (!rst_n)                ?       IDLE:
                                                (weight_number==7 && input_load_number==15)      ?     FIRST_LAYER_ROUND  :
                                                (weight_number==7 && input_load_number <15)      ?     FIRST_LAYER_LDDAT2 :
                                                FIRST_LAYER_ROUND   ;

        FIRST_LAYER_ROUND   :    state_next =   (!rst_n)                ?       IDLE:
                                                (weight_number==7 )     ?       OTHER_LAYER_NORMAL  :
                                                FIRST_LAYER_ROUND   ;

        OTHER_LAYER_NORMAL  :   state_next =    (!rst_n)                ?       IDLE:
                                                (weight_number==7 && input_load_number==15)  ?       OTHER_LAYER_NORMAL  :
                                                OTHER_LAYER_NORMAL   ;

        OTHER_LAYER_ROUND   :   state_next =    (!rst_n)                               ?       IDLE:
                                                (weight_number==7  && layer_number<7)  ?      OTHER_LAYER_NORMAL  :
                                                (weight_number==7  && layer_number==7) ?      OUTPUT              :
                                                OTHER_LAYER_ROUND   ;

        OUTPUT              :   state_next =    (!rst_n)    ?       IDLE   :   OUTPUT;

        default: state_next = IDLE;
    endcase
end
///////////////////////////////////////////////////////////
// output assign
///////////////////////////////////////////////////////////
    logic   array_keep_r;
    logic   array_rounder_en_r=0;
    logic   array_input_type_r=0;
    logic   result_valid_o_r=0;

    assign  array_keep=array_keep_r;
    assign   array_rounder_en=array_rounder_en_r;
    assign   array_input_type=array_input_type_r;
    assign   result_valid_o=result_valid_o_r;


    
always_comb begin : OUTPUT_BLOCK
    //dataload_en_i=0;
    array_keep_r=0;
    array_rounder_en_r=0;
    array_input_type_r=0;
    result_valid_o_r=0;
    case (state_cur)
        IDLE : begin
            //dataload_en_i=0;
            array_keep_r=0;
            array_rounder_en_r=0;
            array_input_type_r=0;
            result_valid_o_r=0;
        end
        FIRST_LAYER_LDDAT1 : begin
            //dataload_en_i=1;
            array_keep_r=0;
            array_rounder_en_r=0;
            array_input_type_r=0;
            result_valid_o_r=0;
        end
        FIRST_LAYER_LDDAT2 : begin
            //dataload_en_i=1;
            array_keep_r=1;
            array_rounder_en_r=0;
            array_input_type_r=0;
            result_valid_o_r=0;
        end
        FIRST_LAYER_NORMAL : begin
            //dataload_en_i=1;
            array_keep_r=0;
            array_rounder_en_r=0;
            array_input_type_r=0;
            result_valid_o_r=0;
        end
        FIRST_LAYER_ROUND : begin
            //dataload_en_i=1;
            array_keep_r=0;
            array_rounder_en_r=1;
            array_input_type_r=0;
            result_valid_o_r=0;
        end
        OTHER_LAYER_NORMAL : begin
            //dataload_en_i=1;
            array_keep_r=0;
            array_rounder_en_r=0;
            array_input_type_r=1;
            result_valid_o_r=0;
        end
        OTHER_LAYER_ROUND : begin
            //dataload_en_i=1;
            array_keep_r=0;
            array_rounder_en_r=1;
            array_input_type_r=1;
            result_valid_o_r=0;
        end
        OUTPUT : begin
            //dataload_en_i=0;
            array_keep_r=0;
            array_rounder_en_r=0;
            array_input_type_r=0;
            result_valid_o_r=1;
        end
    endcase
end

endmodule

testbench/controller_FSM_tb.sv
///////////////////////////////////////////////////////////
// Author: woodsning
///////////////////////////////////////////////////////////
`timescale 1ns/1ps

module controller_FSM_tb();
    logic   clk                     ;
    logic   rst_n           ;
    logic  [3:0] input_load_number;//输入input第几排 0-15
    logic   [2:0]layer_number;//计算第几层0-7
    logic   [2:0] weight_number;//0-7  
    logic   result_valid_o;                 
    //dataload
    logic   dataload_weight_valid;
    logic   dataload_input_valid;
    logic   dataload_en_i;
    //pe_array
    logic   array_rounder_vaild;
    logic   array_keep;
    logic   array_rounder_en;
    logic   array_input_type;

    controller_FSM controller_FSM_inst (
            .clk                    (   clk     ),
            .rst_n                  (   rst_n   ),
            .input_load_number      (   input_load_number),//输入input第几排 0-15
            .layer_number           (   layer_number),//计算第几层0-7
            .weight_number          (   weight_number),//0-7  
            .result_valid_o         (   result_valid_o), //o                 
            .dataload_en_i          (   dataload_en_i),
            .dataload_weight_valid  (   dataload_weight_valid),
            .dataload_input_valid   (   dataload_input_valid),
            //pe_array
            .array_rounder_vaild    (   array_rounder_vaild),
            .array_keep             (   array_keep),//o
            .array_rounder_en       (   array_rounder_en),//o
            .array_input_type       (   array_input_type)//o
        );


initial begin
    $dumpfile("out/controller_FSM.vcd"); // 表示dump文件的路径与名字。
    $dumpvars(0,controller_FSM_tb);        // 0表示记录xxx module下的所有信号
end

initial begin
    clk = 0;
    forever #5 clk = ~clk;
end
logic   [3:0] layer,w_num;
logic  [4:0] i_num;
initial begin
    rst_n=0;
    input_load_number= 0;//输入input第几排 0-15
    layer_number= 0;//计算第几层0-7
    weight_number= 0;//0-7              
    dataload_weight_valid= 0;
    dataload_input_valid= 0;
    dataload_en_i= 0;
    array_rounder_vaild= 0;
    #20;
    //idle
    rst_n=1;
    dataload_en_i= 1;
    #10;
    //2
    dataload_weight_valid=1;
    #10;
    //3
    dataload_weight_valid=0;
    #80;
    dataload_input_valid=1;
    //4
    for ( layer=0 ;layer<=7 ;layer++ ) begin
        layer_number = layer;
        if(layer == 0)begin
            for (   i_num =1 ;i_num <=15;i_num++)begin
                for(   w_num = 0; w_num <= 7; w_num ++)begin
                    weight_number =w_num[2:0];
                    #10;
                    dataload_weight_valid =1;
                    dataload_input_valid=0;
                end
                #80;
                input_load_number=i_num[3:0];
                dataload_input_valid=1;
                dataload_weight_valid =0; 
            end
        end
        else begin
            for (   i_num =0 ;i_num <=15;i_num++)begin
                for(   w_num = 0; w_num <=7; w_num ++)begin
                    input_load_number=i_num;
                    weight_number =w_num;
                    #10;
                end
            end
        end     
    end
    #2560;
    rst_n=0;
    $finish;
end

endmodule

out/controller_FSM.vcd
$date
	Tue May  9 16:32:20 2023
$end

$version
	Synopsys VCS version S-2021.09_Full64
$end

$timescale
	1ps
$end

$comment Csum: 1 fc47282a140a9b48 $end


$scope module controller_FSM_tb $end
$var reg 1 ! clk $end
$var reg 1 " rst_n $end
$var reg 4 # input_load_number [3:0] $end
$var reg 3 $ layer_number [2:0] $end
$var reg 3 % weight_number [2:0] $end
$var reg 1 & result_valid_o $end
$var reg 1 ' dataload_weight_valid $end
$var reg 1 ( dataload_input_valid $end
$var reg 1 ) dataload_en_i $end
$var reg 1 * array_rounder_vaild $end
$var reg 1 + array_keep $end
$var reg 1 , array_rounder_en $end
$var reg 1 - array_input_type $end
$var reg 4 . layer [3:0] $end
$var reg 4 / w_num [3:0] $end
$var reg 5 0 i_num [4:0] $end

$scope module controller_FSM_inst $end
$var wire 1 1 clk $end
$var wire 1 2 rst_n $end
$var wire 4 3 input_load_number [3:0] $end
$var wire 3 4 layer_number [2:0] $end
$var wire 3 5 weight_number [2:0] $end
$var wire 1 6 result_valid_o $end
$var wire 1 7 dataload_weight_valid $end
$var wire 1 8 dataload_input_valid $end
$var wire 1 9 dataload_en_i $end
$var wire 1 : array_rounder_vaild $end
$var wire 1 ; array_keep $end
$var wire 1 < array_rounder_en $end
$var wire 1 = array_input_type $end
$var reg 4 > state_cur [3:0] $end
$var reg 4 ? state_next [3:0] $end
$var reg 1 @ array_keep_r $end
$var reg 1 A array_rounder_en_r $end
$var reg 1 B array_input_type_r $end
$var reg 1 C result_valid_o_r $end

$scope begin N_state $end
$upscope $end


$scope begin OUTPUT_BLOCK $end
$upscope $end

$upscope $end

$upscope $end

$enddefinitions $end

#0
$dumpvars
0-
0B
0+
0@
0,
0A
0*
0!
0=
0;
0<
0:
09
08
07
06
02
0)
0(
0'
0&
0C
0"
b0000 3
b000 4
b000 5
bxxxxx 0
b0000 #
bxxxx .
b000 $
bxxxx >
b0000 ?
bxxxx /
b000 %
01
$end
#5000
1!
11
b0000 >
#10000
0!
01
#15000
1!
11
#20000
1"
12
1)
19
0!
01
b0001 ?
#25000
1!
11
b0001 >
#30000
1'
17
0!
01
b0010 ?
#35000
1!
11
b0010 >
1@
1;
1+
#40000
0'
07
0!
01
#45000
1!
11
#50000
0!
01
#55000
1!
11
#60000
0!
01
#65000
1!
11
#70000
0!
01
#75000
1!
11
#80000
0!
01
#85000
1!
11
#90000
0!
01
#95000
1!
11
#100000
0!
01
#105000
1!
11
#110000
0!
01
#115000
1!
11
#120000
1(
18
b0000 .
b00001 0
b0000 /
0!
01
b0011 ?
#125000
1!
11
b0011 >
b0100 ?
0@
0;
0+
#130000
1'
17
0(
08
b0001 /
b001 %
b001 5
0!
01
#135000
1!
11
b0100 >
1A
1<
1,
#140000
b0010 /
b010 %
b010 5
0!
01
#145000
1!
11
#150000
b0011 /
b011 %
b011 5
0!
01
#155000
1!
11
#160000
b0100 /
b100 %
b100 5
0!
01
#165000
1!
11
#170000
b0101 /
b101 %
b101 5
0!
01
#175000
1!
11
#180000
b0110 /
b110 %
b110 5
0!
01
#185000
1!
11
#190000
b0111 /
b111 %
b111 5
0!
01
b0101 ?
#195000
1!
11
b0101 >
1B
1=
1-
0A
0<
0,
#200000
b1000 /
0!
01
#205000
1!
11
#210000
0!
01
#215000
1!
11
#220000
0!
01
#225000
1!
11
#230000
0!
01
#235000
1!
11
#240000
0!
01
#245000
1!
11
#250000
0!
01
#255000
1!
11
#260000
0!
01
#265000
1!
11
#270000
0!
01
#275000
1!
11
#280000
b0001 #
b0001 3
1(
18
0'
07
b00010 0
b0000 /
b000 %
b000 5
0!
01
#285000
1!
11
#290000
1'
17
0(
08
b0001 /
b001 %
b001 5
0!
01
#295000
1!
11
#300000
b0010 /
b010 %
b010 5
0!
01
#305000
1!
11
#310000
b0011 /
b011 %
b011 5
0!
01
#315000
1!
11
#320000
b0100 /
b100 %
b100 5
0!
01
#325000
1!
11
#330000
b0101 /
b101 %
b101 5
0!
01
#335000
1!
11
#340000
b0110 /
b110 %
b110 5
0!
01
#345000
1!
11
#350000
b0111 /
b111 %
b111 5
0!
01
#355000
1!
11
#360000
b1000 /
0!
01
#365000
1!
11
#370000
0!
01
#375000
1!
11
#380000
0!
01
#385000
1!
11
#390000
0!
01
#395000
1!
11
#400000
0!
01
#405000
1!
11
#410000
0!
01
#415000
1!
11
#420000
0!
01
#425000
1!
11
#430000
0!
01
#435000
1!
11
#440000
b0010 #
b0010 3
1(
18
0'
07
b00011 0
b0000 /
b000 %
b000 5
0!
01
#445000
1!
11
#450000
1'
17
0(
08
b0001 /
b001 %
b001 5
0!
01
#455000
1!
11
#460000
b0010 /
b010 %
b010 5
0!
01
#465000
1!
11
#470000
b0011 /
b011 %
b011 5
0!
01
#475000
1!
11
#480000
b0100 /
b100 %
b100 5
0!
01
#485000
1!
11
#490000
b0101 /
b101 %
b101 5
0!
01
#495000
1!
11
#500000
b0110 /
b110 %
b110 5
0!
01
#505000
1!
11
#510000
b0111 /
b111 %
b111 5
0!
01
#515000
1!
11
#520000
b1000 /
0!
01
#525000
1!
11
#530000
0!
01
#535000
1!
11
#540000
0!
01
#545000
1!
11
#550000
0!
01
#555000
1!
11
#560000
0!
01
#565000
1!
11
#570000
0!
01
#575000
1!
11
#580000
0!
01
#585000
1!
11
#590000
0!
01
#595000
1!
11
#600000
b0011 #
b0011 3
1(
18
0'
07
b00100 0
b0000 /
b000 %
b000 5
0!
01
#605000
1!
11
#610000
1'
17
0(
08
b0001 /
b001 %
b001 5
0!
01
#615000
1!
11
#620000
b0010 /
b010 %
b010 5
0!
01
#625000
1!
11
#630000
b0011 /
b011 %
b011 5
0!
01
#635000
1!
11
#640000
b0100 /
b100 %
b100 5
0!
01
#645000
1!
11
#650000
b0101 /
b101 %
b101 5
0!
01
#655000
1!
11
#660000
b0110 /
b110 %
b110 5
0!
01
#665000
1!
11
#670000
b0111 /
b111 %
b111 5
0!
01
#675000
1!
11
#680000
b1000 /
0!
01
#685000
1!
11
#690000
0!
01
#695000
1!
11
#700000
0!
01
#705000
1!
11
#710000
0!
01
#715000
1!
11
#720000
0!
01
#725000
1!
11
#730000
0!
01
#735000
1!
11
#740000
0!
01
#745000
1!
11
#750000
0!
01
#755000
1!
11
#760000
b0100 #
b0100 3
1(
18
0'
07
b00101 0
b0000 /
b000 %
b000 5
0!
01
#765000
1!
11
#770000
1'
17
0(
08
b0001 /
b001 %
b001 5
0!
01
#775000
1!
11
#780000
b0010 /
b010 %
b010 5
0!
01
#785000
1!
11
#790000
b0011 /
b011 %
b011 5
0!
01
#795000
1!
11
#800000
b0100 /
b100 %
b100 5
0!
01
#805000
1!
11
#810000
b0101 /
b101 %
b101 5
0!
01
#815000
1!
11
#820000
b0110 /
b110 %
b110 5
0!
01
#825000
1!
11
#830000
b0111 /
b111 %
b111 5
0!
01
#835000
1!
11
#840000
b1000 /
0!
01
#845000
1!
11
#850000
0!
01
#855000
1!
11
#860000
0!
01
#865000
1!
11
#870000
0!
01
#875000
1!
11
#880000
0!
01
#885000
1!
11
#890000
0!
01
#895000
1!
11
#900000
0!
01
#905000
1!
11
#910000
0!
01
#915000
1!
11
#920000
b0101 #
b0101 3
1(
18
0'
07
b00110 0
b0000 /
b000 %
b000 5
0!
01
#925000
1!
11
#930000
1'
17
0(
08
b0001 /
b001 %
b001 5
0!
01
#935000
1!
11
#940000
b0010 /
b010 %
b010 5
0!
01
#945000
1!
11
#950000
b0011 /
b011 %
b011 5
0!
01
#955000
1!
11
#960000
b0100 /
b100 %
b100 5
0!
01
#965000
1!
11
#970000
b0101 /
b101 %
b101 5
0!
01
#975000
1!
11
#980000
b0110 /
b110 %
b110 5
0!
01
#985000
1!
11
#990000
b0111 /
b111 %
b111 5
0!
01
#995000
1!
11
#1000000
b1000 /
0!
01
#1005000
1!
11
#1010000
0!
01
#1015000
1!
11
#1020000
0!
01
#1025000
1!
11
#1030000
0!
01
#1035000
1!
11
#1040000
0!
01
#1045000
1!
11
#1050000
0!
01
#1055000
1!
11
#1060000
0!
01
#1065000
1!
11
#1070000
0!
01
#1075000
1!
11
#1080000
b0110 #
b0110 3
1(
18
0'
07
b00111 0
b0000 /
b000 %
b000 5
0!
01
#1085000
1!
11
#1090000
1'
17
0(
08
b0001 /
b001 %
b001 5
0!
01
#1095000
1!
11
#1100000
b0010 /
b010 %
b010 5
0!
01
#1105000
1!
11
#1110000
b0011 /
b011 %
b011 5
0!
01
#1115000
1!
11
#1120000
b0100 /
b100 %
b100 5
0!
01
#1125000
1!
11
#1130000
b0101 /
b101 %
b101 5
0!
01
#1135000
1!
11
#1140000
b0110 /
b110 %
b110 5
0!
01
#1145000
1!
11
#1150000
b0111 /
b111 %
b111 5
0!
01
#1155000
1!
11
#1160000
b1000 /
0!
01
#1165000
1!
11
#1170000
0!
01
#1175000
1!
11
#1180000
0!
01
#1185000
1!
11
#1190000
0!
01
#1195000
1!
11
#1200000
0!
01
#1205000
1!
11
#1210000
0!
01
#1215000
1!
11
#1220000
0!
01
#1225000
1!
11
#1230000
0!
01
#1235000
1!
11
#1240000
b0111 #
b0111 3
1(
18
0'
07
b01000 0
b0000 /
b000 %
b000 5
0!
01
#1245000
1!
11
#1250000
1'
17
0(
08
b0001 /
b001 %
b001 5
0!
01
#1255000
1!
11
#1260000
b0010 /
b010 %
b010 5
0!
01
#1265000
1!
11
#1270000
b0011 /
b011 %
b011 5
0!
01
#1275000
1!
11
#1280000
b0100 /
b100 %
b100 5
0!
01
#1285000
1!
11
#1290000
b0101 /
b101 %
b101 5
0!
01
#1295000
1!
11
#1300000
b0110 /
b110 %
b110 5
0!
01
#1305000
1!
11
#1310000
b0111 /
b111 %
b111 5
0!
01
#1315000
1!
11
#1320000
b1000 /
0!
01
#1325000
1!
11
#1330000
0!
01
#1335000
1!
11
#1340000
0!
01
#1345000
1!
11
#1350000
0!
01
#1355000
1!
11
#1360000
0!
01
#1365000
1!
11
#1370000
0!
01
#1375000
1!
11
#1380000
0!
01
#1385000
1!
11
#1390000
0!
01
#1395000
1!
11
#1400000
b1000 #
b1000 3
1(
18
0'
07
b01001 0
b0000 /
b000 %
b000 5
0!
01
#1405000
1!
11
#1410000
1'
17
0(
08
b0001 /
b001 %
b001 5
0!
01
#1415000
1!
11
#1420000
b0010 /
b010 %
b010 5
0!
01
#1425000
1!
11
#1430000
b0011 /
b011 %
b011 5
0!
01
#1435000
1!
11
#1440000
b0100 /
b100 %
b100 5
0!
01
#1445000
1!
11
#1450000
b0101 /
b101 %
b101 5
0!
01
#1455000
1!
11
#1460000
b0110 /
b110 %
b110 5
0!
01
#1465000
1!
11
#1470000
b0111 /
b111 %
b111 5
0!
01
#1475000
1!
11
#1480000
b1000 /
0!
01
#1485000
1!
11
#1490000
0!
01
#1495000
1!
11
#1500000
0!
01
#1505000
1!
11
#1510000
0!
01
#1515000
1!
11
#1520000
0!
01
#1525000
1!
11
#1530000
0!
01
#1535000
1!
11
#1540000
0!
01
#1545000
1!
11
#1550000
0!
01
#1555000
1!
11
#1560000
b1001 #
b1001 3
1(
18
0'
07
b01010 0
b0000 /
b000 %
b000 5
0!
01
#1565000
1!
11
#1570000
1'
17
0(
08
b0001 /
b001 %
b001 5
0!
01
#1575000
1!
11
#1580000
b0010 /
b010 %
b010 5
0!
01
#1585000
1!
11
#1590000
b0011 /
b011 %
b011 5
0!
01
#1595000
1!
11
#1600000
b0100 /
b100 %
b100 5
0!
01
#1605000
1!
11
#1610000
b0101 /
b101 %
b101 5
0!
01
#1615000
1!
11
#1620000
b0110 /
b110 %
b110 5
0!
01
#1625000
1!
11
#1630000
b0111 /
b111 %
b111 5
0!
01
#1635000
1!
11
#1640000
b1000 /
0!
01
#1645000
1!
11
#1650000
0!
01
#1655000
1!
11
#1660000
0!
01
#1665000
1!
11
#1670000
0!
01
#1675000
1!
11
#1680000
0!
01
#1685000
1!
11
#1690000
0!
01
#1695000
1!
11
#1700000
0!
01
#1705000
1!
11
#1710000
0!
01
#1715000
1!
11
#1720000
b1010 #
b1010 3
1(
18
0'
07
b01011 0
b0000 /
b000 %
b000 5
0!
01
#1725000
1!
11
#1730000
1'
17
0(
08
b0001 /
b001 %
b001 5
0!
01
#1735000
1!
11
#1740000
b0010 /
b010 %
b010 5
0!
01
#1745000
1!
11
#1750000
b0011 /
b011 %
b011 5
0!
01
#1755000
1!
11
#1760000
b0100 /
b100 %
b100 5
0!
01
#1765000
1!
11
#1770000
b0101 /
b101 %
b101 5
0!
01
#1775000
1!
11
#1780000
b0110 /
b110 %
b110 5
0!
01
#1785000
1!
11
#1790000
b0111 /
b111 %
b111 5
0!
01
#1795000
1!
11
#1800000
b1000 /
0!
01
#1805000
1!
11
#1810000
0!
01
#1815000
1!
11
#1820000
0!
01
#1825000
1!
11
#1830000
0!
01
#1835000
1!
11
#1840000
0!
01
#1845000
1!
11
#1850000
0!
01
#1855000
1!
11
#1860000
0!
01
#1865000
1!
11
#1870000
0!
01
#1875000
1!
11
#1880000
b1011 #
b1011 3
1(
18
0'
07
b01100 0
b0000 /
b000 %
b000 5
0!
01
#1885000
1!
11
#1890000
1'
17
0(
08
b0001 /
b001 %
b001 5
0!
01
#1895000
1!
11
#1900000
b0010 /
b010 %
b010 5
0!
01
#1905000
1!
11
#1910000
b0011 /
b011 %
b011 5
0!
01
#1915000
1!
11
#1920000
b0100 /
b100 %
b100 5
0!
01
#1925000
1!
11
#1930000
b0101 /
b101 %
b101 5
0!
01
#1935000
1!
11
#1940000
b0110 /
b110 %
b110 5
0!
01
#1945000
1!
11
#1950000
b0111 /
b111 %
b111 5
0!
01
#1955000
1!
11
#1960000
b1000 /
0!
01
#1965000
1!
11
#1970000
0!
01
#1975000
1!
11
#1980000
0!
01
#1985000
1!
11
#1990000
0!
01
#1995000
1!
11
#2000000
0!
01
#2005000
1!
11
#2010000
0!
01
#2015000
1!
11
#2020000
0!
01
#2025000
1!
11
#2030000
0!
01
#2035000
1!
11
#2040000
b1100 #
b1100 3
1(
18
0'
07
b01101 0
b0000 /
b000 %
b000 5
0!
01
#2045000
1!
11
#2050000
1'
17
0(
08
b0001 /
b001 %
b001 5
0!
01
#2055000
1!
11
#2060000
b0010 /
b010 %
b010 5
0!
01
#2065000
1!
11
#2070000
b0011 /
b011 %
b011 5
0!
01
#2075000
1!
11
#2080000
b0100 /
b100 %
b100 5
0!
01
#2085000
1!
11
#2090000
b0101 /
b101 %
b101 5
0!
01
#2095000
1!
11
#2100000
b0110 /
b110 %
b110 5
0!
01
#2105000
1!
11
#2110000
b0111 /
b111 %
b111 5
0!
01
#2115000
1!
11
#2120000
b1000 /
0!
01
#2125000
1!
11
#2130000
0!
01
#2135000
1!
11
#2140000
0!
01
#2145000
1!
11
#2150000
0!
01
#2155000
1!
11
#2160000
0!
01
#2165000
1!
11
#2170000
0!
01
#2175000
1!
11
#2180000
0!
01
#2185000
1!
11
#2190000
0!
01
#2195000
1!
11
#2200000
b1101 #
b1101 3
1(
18
0'
07
b01110 0
b0000 /
b000 %
b000 5
0!
01
#2205000
1!
11
#2210000
1'
17
0(
08
b0001 /
b001 %
b001 5
0!
01
#2215000
1!
11
#2220000
b0010 /
b010 %
b010 5
0!
01
#2225000
1!
11
#2230000
b0011 /
b011 %
b011 5
0!
01
#2235000
1!
11
#2240000
b0100 /
b100 %
b100 5
0!
01
#2245000
1!
11
#2250000
b0101 /
b101 %
b101 5
0!
01
#2255000
1!
11
#2260000
b0110 /
b110 %
b110 5
0!
01
#2265000
1!
11
#2270000
b0111 /
b111 %
b111 5
0!
01
#2275000
1!
11
#2280000
b1000 /
0!
01
#2285000
1!
11
#2290000
0!
01
#2295000
1!
11
#2300000
0!
01
#2305000
1!
11
#2310000
0!
01
#2315000
1!
11
#2320000
0!
01
#2325000
1!
11
#2330000
0!
01
#2335000
1!
11
#2340000
0!
01
#2345000
1!
11
#2350000
0!
01
#2355000
1!
11
#2360000
b1110 #
b1110 3
1(
18
0'
07
b01111 0
b0000 /
b000 %
b000 5
0!
01
#2365000
1!
11
#2370000
1'
17
0(
08
b0001 /
b001 %
b001 5
0!
01
#2375000
1!
11
#2380000
b0010 /
b010 %
b010 5
0!
01
#2385000
1!
11
#2390000
b0011 /
b011 %
b011 5
0!
01
#2395000
1!
11
#2400000
b0100 /
b100 %
b100 5
0!
01
#2405000
1!
11
#2410000
b0101 /
b101 %
b101 5
0!
01
#2415000
1!
11
#2420000
b0110 /
b110 %
b110 5
0!
01
#2425000
1!
11
#2430000
b0111 /
b111 %
b111 5
0!
01
#2435000
1!
11
#2440000
b1000 /
0!
01
#2445000
1!
11
#2450000
0!
01
#2455000
1!
11
#2460000
0!
01
#2465000
1!
11
#2470000
0!
01
#2475000
1!
11
#2480000
0!
01
#2485000
1!
11
#2490000
0!
01
#2495000
1!
11
#2500000
0!
01
#2505000
1!
11
#2510000
0!
01
#2515000
1!
11
#2520000
b1111 #
b1111 3
1(
18
0'
07
b10000 0
b0001 .
b001 $
b001 4
b00000 0
b0000 /
b0000 #
b0000 3
b000 %
b000 5
0!
01
#2525000
1!
11
#2530000
b0001 /
b001 %
b001 5
0!
01
#2535000
1!
11
#2540000
b0010 /
b010 %
b010 5
0!
01
#2545000
1!
11
#2550000
b0011 /
b011 %
b011 5
0!
01
#2555000
1!
11
#2560000
b0100 /
b100 %
b100 5
0!
01
#2565000
1!
11
#2570000
b0101 /
b101 %
b101 5
0!
01
#2575000
1!
11
#2580000
b0110 /
b110 %
b110 5
0!
01
#2585000
1!
11
#2590000
b0111 /
b111 %
b111 5
0!
01
#2595000
1!
11
#2600000
b1000 /
b00001 0
b0000 /
b0001 #
b0001 3
b000 %
b000 5
0!
01
#2605000
1!
11
#2610000
b0001 /
b001 %
b001 5
0!
01
#2615000
1!
11
#2620000
b0010 /
b010 %
b010 5
0!
01
#2625000
1!
11
#2630000
b0011 /
b011 %
b011 5
0!
01
#2635000
1!
11
#2640000
b0100 /
b100 %
b100 5
0!
01
#2645000
1!
11
#2650000
b0101 /
b101 %
b101 5
0!
01
#2655000
1!
11
#2660000
b0110 /
b110 %
b110 5
0!
01
#2665000
1!
11
#2670000
b0111 /
b111 %
b111 5
0!
01
#2675000
1!
11
#2680000
b1000 /
b00010 0
b0000 /
b0010 #
b0010 3
b000 %
b000 5
0!
01
#2685000
1!
11
#2690000
b0001 /
b001 %
b001 5
0!
01
#2695000
1!
11
#2700000
b0010 /
b010 %
b010 5
0!
01
#2705000
1!
11
#2710000
b0011 /
b011 %
b011 5
0!
01
#2715000
1!
11
#2720000
b0100 /
b100 %
b100 5
0!
01
#2725000
1!
11
#2730000
b0101 /
b101 %
b101 5
0!
01
#2735000
1!
11
#2740000
b0110 /
b110 %
b110 5
0!
01
#2745000
1!
11
#2750000
b0111 /
b111 %
b111 5
0!
01
#2755000
1!
11
#2760000
b1000 /
b00011 0
b0000 /
b0011 #
b0011 3
b000 %
b000 5
0!
01
#2765000
1!
11
#2770000
b0001 /
b001 %
b001 5
0!
01
#2775000
1!
11
#2780000
b0010 /
b010 %
b010 5
0!
01
#2785000
1!
11
#2790000
b0011 /
b011 %
b011 5
0!
01
#2795000
1!
11
#2800000
b0100 /
b100 %
b100 5
0!
01
#2805000
1!
11
#2810000
b0101 /
b101 %
b101 5
0!
01
#2815000
1!
11
#2820000
b0110 /
b110 %
b110 5
0!
01
#2825000
1!
11
#2830000
b0111 /
b111 %
b111 5
0!
01
#2835000
1!
11
#2840000
b1000 /
b00100 0
b0000 /
b0100 #
b0100 3
b000 %
b000 5
0!
01
#2845000
1!
11
#2850000
b0001 /
b001 %
b001 5
0!
01
#2855000
1!
11
#2860000
b0010 /
b010 %
b010 5
0!
01
#2865000
1!
11
#2870000
b0011 /
b011 %
b011 5
0!
01
#2875000
1!
11
#2880000
b0100 /
b100 %
b100 5
0!
01
#2885000
1!
11
#2890000
b0101 /
b101 %
b101 5
0!
01
#2895000
1!
11
#2900000
b0110 /
b110 %
b110 5
0!
01
#2905000
1!
11
#2910000
b0111 /
b111 %
b111 5
0!
01
#2915000
1!
11
#2920000
b1000 /
b00101 0
b0000 /
b0101 #
b0101 3
b000 %
b000 5
0!
01
#2925000
1!
11
#2930000
b0001 /
b001 %
b001 5
0!
01
#2935000
1!
11
#2940000
b0010 /
b010 %
b010 5
0!
01
#2945000
1!
11
#2950000
b0011 /
b011 %
b011 5
0!
01
#2955000
1!
11
#2960000
b0100 /
b100 %
b100 5
0!
01
#2965000
1!
11
#2970000
b0101 /
b101 %
b101 5
0!
01
#2975000
1!
11
#2980000
b0110 /
b110 %
b110 5
0!
01
#2985000
1!
11
#2990000
b0111 /
b111 %
b111 5
0!
01
#2995000
1!
11
#3000000
b1000 /
b00110 0
b0000 /
b0110 #
b0110 3
b000 %
b000 5
0!
01
#3005000
1!
11
#3010000
b0001 /
b001 %
b001 5
0!
01
#3015000
1!
11
#3020000
b0010 /
b010 %
b010 5
0!
01
#3025000
1!
11
#3030000
b0011 /
b011 %
b011 5
0!
01
#3035000
1!
11
#3040000
b0100 /
b100 %
b100 5
0!
01
#3045000
1!
11
#3050000
b0101 /
b101 %
b101 5
0!
01
#3055000
1!
11
#3060000
b0110 /
b110 %
b110 5
0!
01
#3065000
1!
11
#3070000
b0111 /
b111 %
b111 5
0!
01
#3075000
1!
11
#3080000
b1000 /
b00111 0
b0000 /
b0111 #
b0111 3
b000 %
b000 5
0!
01
#3085000
1!
11
#3090000
b0001 /
b001 %
b001 5
0!
01
#3095000
1!
11
#3100000
b0010 /
b010 %
b010 5
0!
01
#3105000
1!
11
#3110000
b0011 /
b011 %
b011 5
0!
01
#3115000
1!
11
#3120000
b0100 /
b100 %
b100 5
0!
01
#3125000
1!
11
#3130000
b0101 /
b101 %
b101 5
0!
01
#3135000
1!
11
#3140000
b0110 /
b110 %
b110 5
0!
01
#3145000
1!
11
#3150000
b0111 /
b111 %
b111 5
0!
01
#3155000
1!
11
#3160000
b1000 /
b01000 0
b0000 /
b1000 #
b1000 3
b000 %
b000 5
0!
01
#3165000
1!
11
#3170000
b0001 /
b001 %
b001 5
0!
01
#3175000
1!
11
#3180000
b0010 /
b010 %
b010 5
0!
01
#3185000
1!
11
#3190000
b0011 /
b011 %
b011 5
0!
01
#3195000
1!
11
#3200000
b0100 /
b100 %
b100 5
0!
01
#3205000
1!
11
#3210000
b0101 /
b101 %
b101 5
0!
01
#3215000
1!
11
#3220000
b0110 /
b110 %
b110 5
0!
01
#3225000
1!
11
#3230000
b0111 /
b111 %
b111 5
0!
01
#3235000
1!
11
