design/shift_buffer.sv
module shift_buffer #(
    parameter buffer_SIZE=8,
    parameter buffer_WIDTH=32
)
(
    input           clk,
    input           rst_n   ,
    input  [buffer_WIDTH-1:0]   data_i  ,
    input           wr_en_i ,
    output [buffer_WIDTH*buffer_SIZE-1:0]  data_o  ,
    output          data_valid_o
);

logic [buffer_WIDTH*buffer_SIZE-1:0]  buffer, buffer_reg;
logic [buffer_WIDTH*buffer_SIZE-1:0]  data_o_r;
logic [3:0]                           cnt, cnt_reg;

always_ff @( posedge clk ) begin
    if (rst_n) begin
        buffer_reg <= buffer;
        cnt_reg <= cnt;
        if (cnt_reg == buffer_SIZE-1) begin
            data_o_r <= buffer;
        end
    end else begin
        // reset
        buffer_reg <= 0;
        cnt_reg <= 0;
        data_o_r <= 0;
    end
end

always_comb begin
    buffer = buffer_reg;
    cnt = cnt_reg;
    if (wr_en_i) begin
        buffer = {buffer_reg[223:0], data_i};
        cnt = cnt_reg + 1'b1;
    end

    if (cnt_reg == buffer_SIZE-1) begin
        cnt = 0;
    end
end
logic data_valid_o_r;
always_ff @(posedge clk)begin
     data_valid_o_r <= (cnt_reg == buffer_SIZE-1) && wr_en_i;
end
assign data_valid_o=data_valid_o_r;
assign data_o = data_o_r;
    
endmodule

design/shift_buffer2.sv
module shift_buffer2 #(
    parameter buffer_SIZE=8,
    parameter buffer_WIDTH=32
)
(
    input           clk,
    input           rst_n   ,
    input  [buffer_WIDTH-1:0]   data_i  ,
    input           wr_en_i ,
    output [buffer_WIDTH*buffer_SIZE-1:0]  data_o  ,
    output          data_valid_o
);

logic [buffer_WIDTH*buffer_SIZE-1:0]  buffer, buffer_reg;
logic [buffer_WIDTH*buffer_SIZE-1:0]  data_o_r;
logic [3:0]                           cnt, cnt_reg;

always_ff @( posedge clk ) begin
    if (rst_n) begin
        buffer_reg <= buffer;
        cnt_reg <= cnt;
        if (cnt_reg == buffer_SIZE-1) begin
            data_o_r <= buffer;
        end
    end else begin
        // reset
        buffer_reg <= 0;
        cnt_reg <= 0;
        data_o_r <= 0;
    end
end

always_comb begin
    buffer = buffer_reg;
    cnt = cnt_reg;
    if (wr_en_i) begin
        buffer = {data_i};
        cnt = cnt_reg + 1'b1;
    end

    if (cnt_reg == buffer_SIZE-1) begin
        cnt = 0;
    end
end
logic data_valid_o_r;
always_ff @(posedge clk)begin
     data_valid_o_r <= (cnt_reg == buffer_SIZE-1) && wr_en_i;
end
assign data_valid_o=data_valid_o_r;
assign data_o = data_o_r;
    
endmodule

design/dataload.sv
module dataload(
    input           clk,
    input           rst_n,
    input  [31:0]   data_i,
    input           load_en_i,
    input           load_type,//0-weight,1-input
    output [255:0]  first_level_input_data,
    output [31:0]   weight_o, 
    output          weight_valid,
    output          input_valid    
);
    logic weight_wr_en,input_wr_en;
    shift_buffer2 #(.buffer_SIZE(1),.buffer_WIDTH(32)
    ) weight_buffer_inst (
        .clk(clk),
        .rst_n(rst_n)   ,
        .data_i(data_i)  ,
        .wr_en_i(weight_wr_en) ,
        .data_o(weight_o)  ,
        .data_valid_o(weight_valid)
    );
    
    shift_buffer input_buffer_inst (
        .clk(clk),
        .rst_n(rst_n)   ,
        .data_i(data_i)  ,
        .wr_en_i(input_wr_en) ,
        .data_o(first_level_input_data)  ,
        .data_valid_o(input_valid)
    );

    always_comb begin: enable_select
    case ({load_en_i,load_type})
        2'b11: begin//输入到input
            weight_wr_en=0;
            input_wr_en=1;
        end
        2'b10: begin//输入到weight
            weight_wr_en=1;
            input_wr_en=0;
        end
        default: begin
            weight_wr_en=0;
            input_wr_en=0;
        end
    endcase
    end
endmodule

testbench/dataload_tb.sv
`timescale 1ns/1ps
module dataload_tb();
    logic           clk  ;
    logic           rst_n       ;
    logic [31:0]    data_i      ;
    logic           load_en_i     ;
    logic           load_en_i;
    logic           load_type;//0-weight,1-input
    logic [255:0]  first_level_input_data;
    logic [31:0]   weight_o;
    logic           weight_valid,input_valid;
    dataload dataload_inst (
        .clk(clk),
        .rst_n(rst_n),
        .data_i(data_i),
        .load_en_i(load_en_i),
        .load_type(load_type),
        .first_level_input_data(first_level_input_data),
        .weight_o(weight_o),
        .weight_valid(weight_valid),
        .input_valid(input_valid)   
    );

    initial begin
        $dumpfile("./out/dataload_tb.vcd");
        $dumpvars(0, dataload_tb);
    end

    initial begin
        clk = 0;
        forever #5 clk = ~clk;
    end

    integer i;

    initial begin
        rst_n = 0;
        data_i = 0;
        load_en_i =0;
        load_type =0;
        #100;
        rst_n = 1;
        #10;
        load_en_i = 1;
        load_type =1;
        for (i = 0; i<8 ; i++ ) begin
            data_i = i+10;
            #10;
        end
        load_en_i = 1;
        load_type =0;
        for (i = 0; i<8 ; i++ ) begin
            data_i = i+20;
            #10;
        end
        load_en_i = 0;
        #100;
        rst_n = 0;
        #100;
        $finish;
    end
        
endmodule

out/dataload_tb.vcd
$date
	Tue May  9 18:48:13 2023
$end

$version
	Synopsys VCS version S-2021.09_Full64
$end

$timescale
	1ps
$end

$comment Csum: 1 8f9710bfcc8eb4e1 $end


$scope module dataload_tb $end
$var reg 1 ! clk $end
$var reg 1 " rst_n $end
$var reg 32 # data_i [31:0] $end
$var reg 1 $ load_en_i $end
$var reg 1 % load_type $end
$var reg 256 & first_level_input_data [255:0] $end
$var reg 32 ' weight_o [31:0] $end
$var reg 1 ( weight_valid $end
$var reg 1 ) input_valid $end
$var integer 32 * i $end

$scope module dataload_inst $end
$var wire 1 + clk $end
$var wire 1 , rst_n $end
$var wire 32 - data_i [31:0] $end
$var wire 1 . load_en_i $end
$var wire 1 / load_type $end
$var wire 256 0 first_level_input_data [255:0] $end
$var wire 32 1 weight_o [31:0] $end
$var wire 1 2 weight_valid $end
$var wire 1 3 input_valid $end
$var reg 1 4 weight_wr_en $end
$var reg 1 5 input_wr_en $end

$scope begin enable_select $end
$upscope $end


$scope module weight_buffer_inst $end
$var wire 1 + clk $end
$var wire 1 , rst_n $end
$var wire 32 - data_i [31:0] $end
$var wire 1 6 wr_en_i $end
$var wire 32 1 data_o [31:0] $end
$var wire 1 2 data_valid_o $end
$var reg 32 7 buffer [31:0] $end
$var reg 32 8 buffer_reg [31:0] $end
$var reg 32 9 data_o_r [31:0] $end
$var reg 4 : cnt [3:0] $end
$var reg 4 ; cnt_reg [3:0] $end
$var reg 1 < data_valid_o_r $end
$upscope $end


$scope module input_buffer_inst $end
$var wire 1 + clk $end
$var wire 1 , rst_n $end
$var wire 32 - data_i [31:0] $end
$var wire 1 = wr_en_i $end
$var wire 256 0 data_o [255:0] $end
$var wire 1 3 data_valid_o $end
$var reg 256 > buffer [255:0] $end
$var reg 256 ? buffer_reg [255:0] $end
$var reg 256 @ data_o_r [255:0] $end
$var reg 4 A cnt [3:0] $end
$var reg 4 B cnt_reg [3:0] $end
$var reg 1 C data_valid_o_r $end
$upscope $end

$upscope $end

$upscope $end

$enddefinitions $end

#0
$dumpvars
0!
x<
x3
0.
0/
0,
x2
xC
0=
x)
05
0$
0%
0"
x(
04
06
bxxxxxxxxxxxxxxxxxxxxxxxxxxxxxxxx 7
bxxxxxxxxxxxxxxxxxxxxxxxxxxxxxxxx 8
bxxxx :
bxxxx ;
b00000000000000000000000000000000 #
bxxxxxxxxxxxxxxxxxxxxxxxxxxxxxxxx 9
b00000000000000000000000000000000 -
bxxxxxxxxxxxxxxxxxxxxxxxxxxxxxxxxxxxxxxxxxxxxxxxxxxxxxxxxxxxxxxxxxxxxxxxxxxxxxxxxxxxxxxxxxxxxxxxxxxxxxxxxxxxxxxxxxxxxxxxxxxxxxxxxxxxxxxxxxxxxxxxxxxxxxxxxxxxxxxxxxxxxxxxxxxxxxxxxxxxxxxxxxxxxxxxxxxxxxxxxxxxxxxxxxxxxxxxxxxxxxxxxxxxxxxxxxxxxxxxxxxxxxxxxxxxxxxxx 0
bxxxxxxxxxxxxxxxxxxxxxxxxxxxxxxxx 1
bxxxxxxxxxxxxxxxxxxxxxxxxxxxxxxxxxxxxxxxxxxxxxxxxxxxxxxxxxxxxxxxxxxxxxxxxxxxxxxxxxxxxxxxxxxxxxxxxxxxxxxxxxxxxxxxxxxxxxxxxxxxxxxxxxxxxxxxxxxxxxxxxxxxxxxxxxxxxxxxxxxxxxxxxxxxxxxxxxxxxxxxxxxxxxxxxxxxxxxxxxxxxxxxxxxxxxxxxxxxxxxxxxxxxxxxxxxxxxxxxxxxxxxxxxxxxxxxx &
bxxxxxxxxxxxxxxxxxxxxxxxxxxxxxxxx *
bxxxxxxxxxxxxxxxxxxxxxxxxxxxxxxxxxxxxxxxxxxxxxxxxxxxxxxxxxxxxxxxxxxxxxxxxxxxxxxxxxxxxxxxxxxxxxxxxxxxxxxxxxxxxxxxxxxxxxxxxxxxxxxxxxxxxxxxxxxxxxxxxxxxxxxxxxxxxxxxxxxxxxxxxxxxxxxxxxxxxxxxxxxxxxxxxxxxxxxxxxxxxxxxxxxxxxxxxxxxxxxxxxxxxxxxxxxxxxxxxxxxxxxxxxxxxxxxx >
bxxxxxxxxxxxxxxxxxxxxxxxxxxxxxxxxxxxxxxxxxxxxxxxxxxxxxxxxxxxxxxxxxxxxxxxxxxxxxxxxxxxxxxxxxxxxxxxxxxxxxxxxxxxxxxxxxxxxxxxxxxxxxxxxxxxxxxxxxxxxxxxxxxxxxxxxxxxxxxxxxxxxxxxxxxxxxxxxxxxxxxxxxxxxxxxxxxxxxxxxxxxxxxxxxxxxxxxxxxxxxxxxxxxxxxxxxxxxxxxxxxxxxxxxxxxxxxxx ?
bxxxx A
bxxxx B
bxxxxxxxxxxxxxxxxxxxxxxxxxxxxxxxxxxxxxxxxxxxxxxxxxxxxxxxxxxxxxxxxxxxxxxxxxxxxxxxxxxxxxxxxxxxxxxxxxxxxxxxxxxxxxxxxxxxxxxxxxxxxxxxxxxxxxxxxxxxxxxxxxxxxxxxxxxxxxxxxxxxxxxxxxxxxxxxxxxxxxxxxxxxxxxxxxxxxxxxxxxxxxxxxxxxxxxxxxxxxxxxxxxxxxxxxxxxxxxxxxxxxxxxxxxxxxxxx @
bxxxxxxxxxxxxxxxxxxxxxxxxxxxxxxxx '
0+
$end
#5000
1!
1+
b00000000000000000000000000000000 8
b0000 ;
b00000000000000000000000000000000 9
b00000000000000000000000000000000 1
b00000000000000000000000000000000 '
0<
02
0(
b0000000000000000000000000000000000000000000000000000000000000000000000000000000000000000000000000000000000000000000000000000000000000000000000000000000000000000000000000000000000000000000000000000000000000000000000000000000000000000000000000000000000000000 ?
b0000 B
b0000000000000000000000000000000000000000000000000000000000000000000000000000000000000000000000000000000000000000000000000000000000000000000000000000000000000000000000000000000000000000000000000000000000000000000000000000000000000000000000000000000000000000 @
b0000000000000000000000000000000000000000000000000000000000000000000000000000000000000000000000000000000000000000000000000000000000000000000000000000000000000000000000000000000000000000000000000000000000000000000000000000000000000000000000000000000000000000 0
b0000000000000000000000000000000000000000000000000000000000000000000000000000000000000000000000000000000000000000000000000000000000000000000000000000000000000000000000000000000000000000000000000000000000000000000000000000000000000000000000000000000000000000 &
0C
03
0)
b0000 :
b00000000000000000000000000000000 7
b0000 A
b0000000000000000000000000000000000000000000000000000000000000000000000000000000000000000000000000000000000000000000000000000000000000000000000000000000000000000000000000000000000000000000000000000000000000000000000000000000000000000000000000000000000000000 >
#10000
0!
0+
#15000
1!
1+
#20000
0!
0+
#25000
1!
1+
#30000
0!
0+
#35000
1!
1+
#40000
0!
0+
#45000
1!
1+
#50000
0!
0+
#55000
1!
1+
#60000
0!
0+
#65000
1!
1+
#70000
0!
0+
#75000
1!
1+
#80000
0!
0+
#85000
1!
1+
#90000
0!
0+
#95000
1!
1+
#100000
1"
1,
0!
0+
#105000
1!
1+
#110000
1$
1.
1%
1/
b00000000000000000000000000000000 *
b00000000000000000000000000001010 #
b00000000000000000000000000001010 -
0!
0+
15
1=
b0001 A
b0000000000000000000000000000000000000000000000000000000000000000000000000000000000000000000000000000000000000000000000000000000000000000000000000000000000000000000000000000000000000000000000000000000000000000000000000000000000000000000000000000000000001010 >
#115000
1!
1+
b0000000000000000000000000000000000000000000000000000000000000000000000000000000000000000000000000000000000000000000000000000000000000000000000000000000000000000000000000000000000000000000000000000000000000000000000000000000000000000000000000000000000001010 ?
b0001 B
b0010 A
b0000000000000000000000000000000000000000000000000000000000000000000000000000000000000000000000000000000000000000000000000000000000000000000000000000000000000000000000000000000000000000000000000000000000000000000000000000101000000000000000000000000000001010 >
#120000
b00000000000000000000000000000001 *
b00000000000000000000000000001011 #
b00000000000000000000000000001011 -
0!
0+
b0000000000000000000000000000000000000000000000000000000000000000000000000000000000000000000000000000000000000000000000000000000000000000000000000000000000000000000000000000000000000000000000000000000000000000000000000000101000000000000000000000000000001011 >
#125000
1!
1+
b0000000000000000000000000000000000000000000000000000000000000000000000000000000000000000000000000000000000000000000000000000000000000000000000000000000000000000000000000000000000000000000000000000000000000000000000000000101000000000000000000000000000001011 ?
b0010 B
b0011 A
b0000000000000000000000000000000000000000000000000000000000000000000000000000000000000000000000000000000000000000000000000000000000000000000000000000000000000000000000000000000000000000000010100000000000000000000000000000101100000000000000000000000000001011 >
#130000
b00000000000000000000000000000010 *
b00000000000000000000000000001100 #
b00000000000000000000000000001100 -
0!
0+
b0000000000000000000000000000000000000000000000000000000000000000000000000000000000000000000000000000000000000000000000000000000000000000000000000000000000000000000000000000000000000000000010100000000000000000000000000000101100000000000000000000000000001100 >
#135000
1!
1+
b0000000000000000000000000000000000000000000000000000000000000000000000000000000000000000000000000000000000000000000000000000000000000000000000000000000000000000000000000000000000000000000010100000000000000000000000000000101100000000000000000000000000001100 ?
b0011 B
b0100 A
b0000000000000000000000000000000000000000000000000000000000000000000000000000000000000000000000000000000000000000000000000000000000000000000000000000000000001010000000000000000000000000000010110000000000000000000000000000110000000000000000000000000000001100 >
#140000
b00000000000000000000000000000011 *
b00000000000000000000000000001101 #
b00000000000000000000000000001101 -
0!
0+
b0000000000000000000000000000000000000000000000000000000000000000000000000000000000000000000000000000000000000000000000000000000000000000000000000000000000001010000000000000000000000000000010110000000000000000000000000000110000000000000000000000000000001101 >
#145000
1!
1+
b0000000000000000000000000000000000000000000000000000000000000000000000000000000000000000000000000000000000000000000000000000000000000000000000000000000000001010000000000000000000000000000010110000000000000000000000000000110000000000000000000000000000001101 ?
b0100 B
b0101 A
b0000000000000000000000000000000000000000000000000000000000000000000000000000000000000000000000000000000000000000000000000000101000000000000000000000000000001011000000000000000000000000000011000000000000000000000000000000110100000000000000000000000000001101 >
#150000
b00000000000000000000000000000100 *
b00000000000000000000000000001110 #
b00000000000000000000000000001110 -
0!
0+
b0000000000000000000000000000000000000000000000000000000000000000000000000000000000000000000000000000000000000000000000000000101000000000000000000000000000001011000000000000000000000000000011000000000000000000000000000000110100000000000000000000000000001110 >
#155000
1!
1+
b0000000000000000000000000000000000000000000000000000000000000000000000000000000000000000000000000000000000000000000000000000101000000000000000000000000000001011000000000000000000000000000011000000000000000000000000000000110100000000000000000000000000001110 ?
b0101 B
b0110 A
b0000000000000000000000000000000000000000000000000000000000000000000000000000000000000000000010100000000000000000000000000000101100000000000000000000000000001100000000000000000000000000000011010000000000000000000000000000111000000000000000000000000000001110 >
#160000
b00000000000000000000000000000101 *
b00000000000000000000000000001111 #
b00000000000000000000000000001111 -
0!
0+
b0000000000000000000000000000000000000000000000000000000000000000000000000000000000000000000010100000000000000000000000000000101100000000000000000000000000001100000000000000000000000000000011010000000000000000000000000000111000000000000000000000000000001111 >
#165000
1!
1+
b0000000000000000000000000000000000000000000000000000000000000000000000000000000000000000000010100000000000000000000000000000101100000000000000000000000000001100000000000000000000000000000011010000000000000000000000000000111000000000000000000000000000001111 ?
b0110 B
b0111 A
b0000000000000000000000000000000000000000000000000000000000001010000000000000000000000000000010110000000000000000000000000000110000000000000000000000000000001101000000000000000000000000000011100000000000000000000000000000111100000000000000000000000000001111 >
#170000
b00000000000000000000000000000110 *
b00000000000000000000000000010000 #
b00000000000000000000000000010000 -
0!
0+
b0000000000000000000000000000000000000000000000000000000000001010000000000000000000000000000010110000000000000000000000000000110000000000000000000000000000001101000000000000000000000000000011100000000000000000000000000000111100000000000000000000000000010000 >
#175000
1!
1+
b0000000000000000000000000000000000000000000000000000000000001010000000000000000000000000000010110000000000000000000000000000110000000000000000000000000000001101000000000000000000000000000011100000000000000000000000000000111100000000000000000000000000010000 ?
b0111 B
b0000 A
b0000000000000000000000000000101000000000000000000000000000001011000000000000000000000000000011000000000000000000000000000000110100000000000000000000000000001110000000000000000000000000000011110000000000000000000000000001000000000000000000000000000000010000 >
#180000
b00000000000000000000000000000111 *
b00000000000000000000000000010001 #
b00000000000000000000000000010001 -
0!
0+
b0000000000000000000000000000101000000000000000000000000000001011000000000000000000000000000011000000000000000000000000000000110100000000000000000000000000001110000000000000000000000000000011110000000000000000000000000001000000000000000000000000000000010001 >
#185000
1!
1+
b0000000000000000000000000000101000000000000000000000000000001011000000000000000000000000000011000000000000000000000000000000110100000000000000000000000000001110000000000000000000000000000011110000000000000000000000000001000000000000000000000000000000010001 ?
b0000 B
b0000000000000000000000000000101000000000000000000000000000001011000000000000000000000000000011000000000000000000000000000000110100000000000000000000000000001110000000000000000000000000000011110000000000000000000000000001000000000000000000000000000000010001 @
b0000000000000000000000000000101000000000000000000000000000001011000000000000000000000000000011000000000000000000000000000000110100000000000000000000000000001110000000000000000000000000000011110000000000000000000000000001000000000000000000000000000000010001 0
b0000000000000000000000000000101000000000000000000000000000001011000000000000000000000000000011000000000000000000000000000000110100000000000000000000000000001110000000000000000000000000000011110000000000000000000000000001000000000000000000000000000000010001 &
1C
13
1)
b0001 A
b0000000000000000000000000000101100000000000000000000000000001100000000000000000000000000000011010000000000000000000000000000111000000000000000000000000000001111000000000000000000000000000100000000000000000000000000000001000100000000000000000000000000010001 >
#190000
b00000000000000000000000000001000 *
0%
0/
b00000000000000000000000000000000 *
b00000000000000000000000000010100 #
b00000000000000000000000000010100 -
0!
0+
05
0=
14
16
b00000000000000000000000000010100 7
b0000 A
b0000000000000000000000000000101000000000000000000000000000001011000000000000000000000000000011000000000000000000000000000000110100000000000000000000000000001110000000000000000000000000000011110000000000000000000000000001000000000000000000000000000000010001 >
#195000
1!
1+
b00000000000000000000000000010100 8
b00000000000000000000000000010100 9
b00000000000000000000000000010100 1
b00000000000000000000000000010100 '
1<
12
1(
0C
03
0)
#200000
b00000000000000000000000000000001 *
b00000000000000000000000000010101 #
b00000000000000000000000000010101 -
0!
0+
b00000000000000000000000000010101 7
#205000
1!
1+
b00000000000000000000000000010101 8
b00000000000000000000000000010101 9
b00000000000000000000000000010101 1
b00000000000000000000000000010101 '
#210000
b00000000000000000000000000000010 *
b00000000000000000000000000010110 #
b00000000000000000000000000010110 -
0!
0+
b00000000000000000000000000010110 7
#215000
1!
1+
b00000000000000000000000000010110 8
b00000000000000000000000000010110 9
b00000000000000000000000000010110 1
b00000000000000000000000000010110 '
#220000
b00000000000000000000000000000011 *
b00000000000000000000000000010111 #
b00000000000000000000000000010111 -
0!
0+
b00000000000000000000000000010111 7
#225000
1!
1+
b00000000000000000000000000010111 8
b00000000000000000000000000010111 9
b00000000000000000000000000010111 1
b00000000000000000000000000010111 '
#230000
b00000000000000000000000000000100 *
b00000000000000000000000000011000 #
b00000000000000000000000000011000 -
0!
0+
b00000000000000000000000000011000 7
#235000
1!
1+
b00000000000000000000000000011000 8
b00000000000000000000000000011000 9
b00000000000000000000000000011000 1
b00000000000000000000000000011000 '
#240000
b00000000000000000000000000000101 *
b00000000000000000000000000011001 #
b00000000000000000000000000011001 -
0!
0+
b00000000000000000000000000011001 7
#245000
1!
1+
b00000000000000000000000000011001 8
b00000000000000000000000000011001 9
b00000000000000000000000000011001 1
b00000000000000000000000000011001 '
#250000
b00000000000000000000000000000110 *
b00000000000000000000000000011010 #
b00000000000000000000000000011010 -
0!
0+
b00000000000000000000000000011010 7
#255000
1!
1+
b00000000000000000000000000011010 8
b00000000000000000000000000011010 9
b00000000000000000000000000011010 1
b00000000000000000000000000011010 '
#260000
b00000000000000000000000000000111 *
b00000000000000000000000000011011 #
b00000000000000000000000000011011 -
0!
0+
b00000000000000000000000000011011 7
#265000
1!
1+
b00000000000000000000000000011011 8
b00000000000000000000000000011011 9
b00000000000000000000000000011011 1
b00000000000000000000000000011011 '
#270000
b00000000000000000000000000001000 *
0$
0.
0!
0+
04
06
#275000
1!
1+
0<
02
0(
#280000
0!
0+
#285000
1!
1+
#290000
0!
0+
#295000
1!
1+
#300000
0!
0+
#305000
1!
1+
#310000
0!
0+
#315000
1!
1+
#320000
0!
0+
#325000
1!
1+
#330000
0!
0+
#335000
1!
1+
#340000
0!
0+
#345000
1!
1+
#350000
0!
0+
#355000
1!
1+
#360000
0!
0+
#365000
1!
1+
#370000
0"
0,
0!
0+
#375000
1!
1+
b00000000000000000000000000000000 8
b00000000000000000000000000000000 9
b00000000000000000000000000000000 1
b00000000000000000000000000000000 '
b0000000000000000000000000000000000000000000000000000000000000000000000000000000000000000000000000000000000000000000000000000000000000000000000000000000000000000000000000000000000000000000000000000000000000000000000000000000000000000000000000000000000000000 ?
b0000000000000000000000000000000000000000000000000000000000000000000000000000000000000000000000000000000000000000000000000000000000000000000000000000000000000000000000000000000000000000000000000000000000000000000000000000000000000000000000000000000000000000 @
b0000000000000000000000000000000000000000000000000000000000000000000000000000000000000000000000000000000000000000000000000000000000000000000000000000000000000000000000000000000000000000000000000000000000000000000000000000000000000000000000000000000000000000 0
b0000000000000000000000000000000000000000000000000000000000000000000000000000000000000000000000000000000000000000000000000000000000000000000000000000000000000000000000000000000000000000000000000000000000000000000000000000000000000000000000000000000000000000 &
b00000000000000000000000000000000 7
b0000000000000000000000000000000000000000000000000000000000000000000000000000000000000000000000000000000000000000000000000000000000000000000000000000000000000000000000000000000000000000000000000000000000000000000000000000000000000000000000000000000000000000 >
