design/shift_buffer.sv
module shift_buffer #(
    parameter buffer_SIZE=8,
    parameter buffer_WIDTH=32
)
(
    input           clk,
    input           rst_n   ,
    input  [buffer_WIDTH-1:0]   data_i  ,
    input           wr_en_i ,
    output [buffer_WIDTH*buffer_SIZE-1:0]  data_o  ,
    output          data_valid_o
);

logic [buffer_WIDTH*buffer_SIZE-1:0]  buffer, buffer_reg;
logic [buffer_WIDTH*buffer_SIZE-1:0]  data_o_r;
logic [3:0]                           cnt, cnt_reg;

always_ff @( posedge clk ) begin
    if (rst_n) begin
        buffer_reg <= buffer;
        cnt_reg <= cnt;
        if (cnt_reg == buffer_SIZE-1) begin
            data_o_r <= buffer;
        end
    end else begin
        // reset
        buffer_reg <= 0;
        cnt_reg <= 0;
        data_o_r <= 0;
    end
end

always_comb begin
    buffer = buffer_reg;
    cnt = cnt_reg;
    if (wr_en_i) begin
        buffer = {buffer_reg[223:0], data_i};
        cnt = cnt_reg + 1'b1;
    end

    if (cnt_reg == buffer_SIZE-1) begin
        cnt = 0;
    end
end
logic data_valid_o_r;
always_ff @(posedge clk)begin
     data_valid_o_r <= (cnt_reg == buffer_SIZE-1) && wr_en_i;
end
assign data_valid_o=data_valid_o_r;
assign data_o = data_o_r;
    
endmodule

testbench/shiftbuffer_tb.sv
`timescale 1ns/1ps
module shiftbuffer_tb();
    logic           clk  ;
    logic           rst_n       ;
    logic [31:0]    data_i      ;
    logic           wr_en_i     ;
    logic [255:0]   data_o      ;
    logic           data_valid_o;

    shift_buffer shift_buffer_inst (
        .clk(clk),
        .rst_n(rst_n),
        .data_i(data_i),
        .wr_en_i(wr_en_i),
        .data_o(data_o),
        .data_valid_o(data_valid_o)
    );

    initial begin
        $dumpfile("./out/shiftbuffer_tb.vcd");
        $dumpvars(0, shiftbuffer_tb);
    end

    initial begin
        clk = 0;
        forever #5 clk = ~clk;
    end

    integer i;

    initial begin
        rst_n = 0;
        data_i = 0;
        wr_en_i = 0;
        #100;
        rst_n = 1;
        #10;
        wr_en_i = 1;
        for (i = 0; i<8 ; i++ ) begin
            data_i = i+10;
            #10;
        end
        for (i = 0; i<8 ; i++ ) begin
            data_i = i+20;
            #10;
        end
        wr_en_i = 0;
        #100;
        wr_en_i = 1;
        for (i = 0; i<8 ; i++ ) begin
            data_i = i+30;
            #10;
        end
        #100;
        $finish;
    end
        
endmodule

out/shiftbuffer_tb.vcd
$date
	Wed May 10 20:36:49 2023
$end

$version
	Synopsys VCS version S-2021.09_Full64
$end

$timescale
	1ps
$end

$comment Csum: 1 2fc7584f984c1527 $end


$scope module shiftbuffer_tb $end
$var reg 1 ! clk $end
$var reg 1 " rst_n $end
$var reg 32 # data_i [31:0] $end
$var reg 1 $ wr_en_i $end
$var reg 256 % data_o [255:0] $end
$var reg 1 & data_valid_o $end
$var integer 32 ' i $end

$scope module shift_buffer_inst $end
$var wire 1 ( clk $end
$var wire 1 ) rst_n $end
$var wire 32 * data_i [31:0] $end
$var wire 1 + wr_en_i $end
$var wire 256 , data_o [255:0] $end
$var wire 1 - data_valid_o $end
$var reg 256 . buffer [255:0] $end
$var reg 256 / buffer_reg [255:0] $end
$var reg 256 0 data_o_r [255:0] $end
$var reg 4 1 cnt [3:0] $end
$var reg 4 2 cnt_reg [3:0] $end
$var reg 1 3 data_valid_o_r $end
$upscope $end

$upscope $end

$enddefinitions $end

#0
$dumpvars
0!
x&
x3
0"
x-
0)
0+
0$
bxxxxxxxxxxxxxxxxxxxxxxxxxxxxxxxxxxxxxxxxxxxxxxxxxxxxxxxxxxxxxxxxxxxxxxxxxxxxxxxxxxxxxxxxxxxxxxxxxxxxxxxxxxxxxxxxxxxxxxxxxxxxxxxxxxxxxxxxxxxxxxxxxxxxxxxxxxxxxxxxxxxxxxxxxxxxxxxxxxxxxxxxxxxxxxxxxxxxxxxxxxxxxxxxxxxxxxxxxxxxxxxxxxxxxxxxxxxxxxxxxxxxxxxxxxxxxxxx .
bxxxxxxxxxxxxxxxxxxxxxxxxxxxxxxxxxxxxxxxxxxxxxxxxxxxxxxxxxxxxxxxxxxxxxxxxxxxxxxxxxxxxxxxxxxxxxxxxxxxxxxxxxxxxxxxxxxxxxxxxxxxxxxxxxxxxxxxxxxxxxxxxxxxxxxxxxxxxxxxxxxxxxxxxxxxxxxxxxxxxxxxxxxxxxxxxxxxxxxxxxxxxxxxxxxxxxxxxxxxxxxxxxxxxxxxxxxxxxxxxxxxxxxxxxxxxxxxx /
bxxxx 1
bxxxx 2
b00000000000000000000000000000000 #
bxxxxxxxxxxxxxxxxxxxxxxxxxxxxxxxxxxxxxxxxxxxxxxxxxxxxxxxxxxxxxxxxxxxxxxxxxxxxxxxxxxxxxxxxxxxxxxxxxxxxxxxxxxxxxxxxxxxxxxxxxxxxxxxxxxxxxxxxxxxxxxxxxxxxxxxxxxxxxxxxxxxxxxxxxxxxxxxxxxxxxxxxxxxxxxxxxxxxxxxxxxxxxxxxxxxxxxxxxxxxxxxxxxxxxxxxxxxxxxxxxxxxxxxxxxxxxxxx %
bxxxxxxxxxxxxxxxxxxxxxxxxxxxxxxxxxxxxxxxxxxxxxxxxxxxxxxxxxxxxxxxxxxxxxxxxxxxxxxxxxxxxxxxxxxxxxxxxxxxxxxxxxxxxxxxxxxxxxxxxxxxxxxxxxxxxxxxxxxxxxxxxxxxxxxxxxxxxxxxxxxxxxxxxxxxxxxxxxxxxxxxxxxxxxxxxxxxxxxxxxxxxxxxxxxxxxxxxxxxxxxxxxxxxxxxxxxxxxxxxxxxxxxxxxxxxxxxx 0
bxxxxxxxxxxxxxxxxxxxxxxxxxxxxxxxx '
b00000000000000000000000000000000 *
bxxxxxxxxxxxxxxxxxxxxxxxxxxxxxxxxxxxxxxxxxxxxxxxxxxxxxxxxxxxxxxxxxxxxxxxxxxxxxxxxxxxxxxxxxxxxxxxxxxxxxxxxxxxxxxxxxxxxxxxxxxxxxxxxxxxxxxxxxxxxxxxxxxxxxxxxxxxxxxxxxxxxxxxxxxxxxxxxxxxxxxxxxxxxxxxxxxxxxxxxxxxxxxxxxxxxxxxxxxxxxxxxxxxxxxxxxxxxxxxxxxxxxxxxxxxxxxxx ,
0(
$end
#5000
1!
1(
b0000000000000000000000000000000000000000000000000000000000000000000000000000000000000000000000000000000000000000000000000000000000000000000000000000000000000000000000000000000000000000000000000000000000000000000000000000000000000000000000000000000000000000 /
b0000 2
b0000000000000000000000000000000000000000000000000000000000000000000000000000000000000000000000000000000000000000000000000000000000000000000000000000000000000000000000000000000000000000000000000000000000000000000000000000000000000000000000000000000000000000 0
b0000000000000000000000000000000000000000000000000000000000000000000000000000000000000000000000000000000000000000000000000000000000000000000000000000000000000000000000000000000000000000000000000000000000000000000000000000000000000000000000000000000000000000 ,
b0000000000000000000000000000000000000000000000000000000000000000000000000000000000000000000000000000000000000000000000000000000000000000000000000000000000000000000000000000000000000000000000000000000000000000000000000000000000000000000000000000000000000000 %
03
0-
0&
b0000 1
b0000000000000000000000000000000000000000000000000000000000000000000000000000000000000000000000000000000000000000000000000000000000000000000000000000000000000000000000000000000000000000000000000000000000000000000000000000000000000000000000000000000000000000 .
#10000
0!
0(
#15000
1!
1(
#20000
0!
0(
#25000
1!
1(
#30000
0!
0(
#35000
1!
1(
#40000
0!
0(
#45000
1!
1(
#50000
0!
0(
#55000
1!
1(
#60000
0!
0(
#65000
1!
1(
#70000
0!
0(
#75000
1!
1(
#80000
0!
0(
#85000
1!
1(
#90000
0!
0(
#95000
1!
1(
#100000
1"
1)
0!
0(
#105000
1!
1(
#110000
1$
1+
b00000000000000000000000000000000 '
b00000000000000000000000000001010 #
b00000000000000000000000000001010 *
0!
0(
b0001 1
b0000000000000000000000000000101000000000000000000000000000000000000000000000000000000000000000000000000000000000000000000000000000000000000000000000000000000000000000000000000000000000000000000000000000000000000000000000000000000000000000000000000000000000 .
#115000
1!
1(
b0000000000000000000000000000101000000000000000000000000000000000000000000000000000000000000000000000000000000000000000000000000000000000000000000000000000000000000000000000000000000000000000000000000000000000000000000000000000000000000000000000000000000000 /
b0001 2
b0010 1
b0000000000000000000000000000101000000000000000000000000000001010000000000000000000000000000000000000000000000000000000000000000000000000000000000000000000000000000000000000000000000000000000000000000000000000000000000000000000000000000000000000000000000000 .
#120000
b00000000000000000000000000000001 '
b00000000000000000000000000001011 #
b00000000000000000000000000001011 *
0!
0(
b0000000000000000000000000000101100000000000000000000000000001010000000000000000000000000000000000000000000000000000000000000000000000000000000000000000000000000000000000000000000000000000000000000000000000000000000000000000000000000000000000000000000000000 .
#125000
1!
1(
b0000000000000000000000000000101100000000000000000000000000001010000000000000000000000000000000000000000000000000000000000000000000000000000000000000000000000000000000000000000000000000000000000000000000000000000000000000000000000000000000000000000000000000 /
b0010 2
b0011 1
b0000000000000000000000000000101100000000000000000000000000001011000000000000000000000000000010100000000000000000000000000000000000000000000000000000000000000000000000000000000000000000000000000000000000000000000000000000000000000000000000000000000000000000 .
#130000
b00000000000000000000000000000010 '
b00000000000000000000000000001100 #
b00000000000000000000000000001100 *
0!
0(
b0000000000000000000000000000110000000000000000000000000000001011000000000000000000000000000010100000000000000000000000000000000000000000000000000000000000000000000000000000000000000000000000000000000000000000000000000000000000000000000000000000000000000000 .
#135000
1!
1(
b0000000000000000000000000000110000000000000000000000000000001011000000000000000000000000000010100000000000000000000000000000000000000000000000000000000000000000000000000000000000000000000000000000000000000000000000000000000000000000000000000000000000000000 /
b0011 2
b0100 1
b0000000000000000000000000000110000000000000000000000000000001100000000000000000000000000000010110000000000000000000000000000101000000000000000000000000000000000000000000000000000000000000000000000000000000000000000000000000000000000000000000000000000000000 .
#140000
b00000000000000000000000000000011 '
b00000000000000000000000000001101 #
b00000000000000000000000000001101 *
0!
0(
b0000000000000000000000000000110100000000000000000000000000001100000000000000000000000000000010110000000000000000000000000000101000000000000000000000000000000000000000000000000000000000000000000000000000000000000000000000000000000000000000000000000000000000 .
#145000
1!
1(
b0000000000000000000000000000110100000000000000000000000000001100000000000000000000000000000010110000000000000000000000000000101000000000000000000000000000000000000000000000000000000000000000000000000000000000000000000000000000000000000000000000000000000000 /
b0100 2
b0101 1
b0000000000000000000000000000110100000000000000000000000000001101000000000000000000000000000011000000000000000000000000000000101100000000000000000000000000001010000000000000000000000000000000000000000000000000000000000000000000000000000000000000000000000000 .
#150000
b00000000000000000000000000000100 '
b00000000000000000000000000001110 #
b00000000000000000000000000001110 *
0!
0(
b0000000000000000000000000000111000000000000000000000000000001101000000000000000000000000000011000000000000000000000000000000101100000000000000000000000000001010000000000000000000000000000000000000000000000000000000000000000000000000000000000000000000000000 .
#155000
1!
1(
b0000000000000000000000000000111000000000000000000000000000001101000000000000000000000000000011000000000000000000000000000000101100000000000000000000000000001010000000000000000000000000000000000000000000000000000000000000000000000000000000000000000000000000 /
b0101 2
b0110 1
b0000000000000000000000000000111000000000000000000000000000001110000000000000000000000000000011010000000000000000000000000000110000000000000000000000000000001011000000000000000000000000000010100000000000000000000000000000000000000000000000000000000000000000 .
#160000
b00000000000000000000000000000101 '
b00000000000000000000000000001111 #
b00000000000000000000000000001111 *
0!
0(
b0000000000000000000000000000111100000000000000000000000000001110000000000000000000000000000011010000000000000000000000000000110000000000000000000000000000001011000000000000000000000000000010100000000000000000000000000000000000000000000000000000000000000000 .
#165000
1!
1(
b0000000000000000000000000000111100000000000000000000000000001110000000000000000000000000000011010000000000000000000000000000110000000000000000000000000000001011000000000000000000000000000010100000000000000000000000000000000000000000000000000000000000000000 /
b0110 2
b0111 1
b0000000000000000000000000000111100000000000000000000000000001111000000000000000000000000000011100000000000000000000000000000110100000000000000000000000000001100000000000000000000000000000010110000000000000000000000000000101000000000000000000000000000000000 .
#170000
b00000000000000000000000000000110 '
b00000000000000000000000000010000 #
b00000000000000000000000000010000 *
0!
0(
b0000000000000000000000000001000000000000000000000000000000001111000000000000000000000000000011100000000000000000000000000000110100000000000000000000000000001100000000000000000000000000000010110000000000000000000000000000101000000000000000000000000000000000 .
#175000
1!
1(
b0000000000000000000000000001000000000000000000000000000000001111000000000000000000000000000011100000000000000000000000000000110100000000000000000000000000001100000000000000000000000000000010110000000000000000000000000000101000000000000000000000000000000000 /
b0111 2
b0000 1
b0000000000000000000000000001000000000000000000000000000000010000000000000000000000000000000011110000000000000000000000000000111000000000000000000000000000001101000000000000000000000000000011000000000000000000000000000000101100000000000000000000000000001010 .
#180000
b00000000000000000000000000000111 '
b00000000000000000000000000010001 #
b00000000000000000000000000010001 *
0!
0(
b0000000000000000000000000001000100000000000000000000000000010000000000000000000000000000000011110000000000000000000000000000111000000000000000000000000000001101000000000000000000000000000011000000000000000000000000000000101100000000000000000000000000001010 .
#185000
1!
1(
b0000000000000000000000000001000100000000000000000000000000010000000000000000000000000000000011110000000000000000000000000000111000000000000000000000000000001101000000000000000000000000000011000000000000000000000000000000101100000000000000000000000000001010 /
b0000 2
b0000000000000000000000000001000100000000000000000000000000010000000000000000000000000000000011110000000000000000000000000000111000000000000000000000000000001101000000000000000000000000000011000000000000000000000000000000101100000000000000000000000000001010 0
b0000000000000000000000000001000100000000000000000000000000010000000000000000000000000000000011110000000000000000000000000000111000000000000000000000000000001101000000000000000000000000000011000000000000000000000000000000101100000000000000000000000000001010 ,
b0000000000000000000000000001000100000000000000000000000000010000000000000000000000000000000011110000000000000000000000000000111000000000000000000000000000001101000000000000000000000000000011000000000000000000000000000000101100000000000000000000000000001010 %
13
1-
1&
b0001 1
b0000000000000000000000000001000100000000000000000000000000010001000000000000000000000000000100000000000000000000000000000000111100000000000000000000000000001110000000000000000000000000000011010000000000000000000000000000110000000000000000000000000000001011 .
#190000
b00000000000000000000000000001000 '
b00000000000000000000000000000000 '
b00000000000000000000000000010100 #
b00000000000000000000000000010100 *
0!
0(
b0000000000000000000000000001010000000000000000000000000000010001000000000000000000000000000100000000000000000000000000000000111100000000000000000000000000001110000000000000000000000000000011010000000000000000000000000000110000000000000000000000000000001011 .
#195000
1!
1(
b0000000000000000000000000001010000000000000000000000000000010001000000000000000000000000000100000000000000000000000000000000111100000000000000000000000000001110000000000000000000000000000011010000000000000000000000000000110000000000000000000000000000001011 /
b0001 2
03
0-
0&
b0010 1
b0000000000000000000000000001010000000000000000000000000000010100000000000000000000000000000100010000000000000000000000000001000000000000000000000000000000001111000000000000000000000000000011100000000000000000000000000000110100000000000000000000000000001100 .
#200000
b00000000000000000000000000000001 '
b00000000000000000000000000010101 #
b00000000000000000000000000010101 *
0!
0(
b0000000000000000000000000001010100000000000000000000000000010100000000000000000000000000000100010000000000000000000000000001000000000000000000000000000000001111000000000000000000000000000011100000000000000000000000000000110100000000000000000000000000001100 .
#205000
1!
1(
b0000000000000000000000000001010100000000000000000000000000010100000000000000000000000000000100010000000000000000000000000001000000000000000000000000000000001111000000000000000000000000000011100000000000000000000000000000110100000000000000000000000000001100 /
b0010 2
b0011 1
b0000000000000000000000000001010100000000000000000000000000010101000000000000000000000000000101000000000000000000000000000001000100000000000000000000000000010000000000000000000000000000000011110000000000000000000000000000111000000000000000000000000000001101 .
#210000
b00000000000000000000000000000010 '
b00000000000000000000000000010110 #
b00000000000000000000000000010110 *
0!
0(
b0000000000000000000000000001011000000000000000000000000000010101000000000000000000000000000101000000000000000000000000000001000100000000000000000000000000010000000000000000000000000000000011110000000000000000000000000000111000000000000000000000000000001101 .
#215000
1!
1(
b0000000000000000000000000001011000000000000000000000000000010101000000000000000000000000000101000000000000000000000000000001000100000000000000000000000000010000000000000000000000000000000011110000000000000000000000000000111000000000000000000000000000001101 /
b0011 2
b0100 1
b0000000000000000000000000001011000000000000000000000000000010110000000000000000000000000000101010000000000000000000000000001010000000000000000000000000000010001000000000000000000000000000100000000000000000000000000000000111100000000000000000000000000001110 .
#220000
b00000000000000000000000000000011 '
b00000000000000000000000000010111 #
b00000000000000000000000000010111 *
0!
0(
b0000000000000000000000000001011100000000000000000000000000010110000000000000000000000000000101010000000000000000000000000001010000000000000000000000000000010001000000000000000000000000000100000000000000000000000000000000111100000000000000000000000000001110 .
#225000
1!
1(
b0000000000000000000000000001011100000000000000000000000000010110000000000000000000000000000101010000000000000000000000000001010000000000000000000000000000010001000000000000000000000000000100000000000000000000000000000000111100000000000000000000000000001110 /
b0100 2
b0101 1
b0000000000000000000000000001011100000000000000000000000000010111000000000000000000000000000101100000000000000000000000000001010100000000000000000000000000010100000000000000000000000000000100010000000000000000000000000001000000000000000000000000000000001111 .
#230000
b00000000000000000000000000000100 '
b00000000000000000000000000011000 #
b00000000000000000000000000011000 *
0!
0(
b0000000000000000000000000001100000000000000000000000000000010111000000000000000000000000000101100000000000000000000000000001010100000000000000000000000000010100000000000000000000000000000100010000000000000000000000000001000000000000000000000000000000001111 .
#235000
1!
1(
b0000000000000000000000000001100000000000000000000000000000010111000000000000000000000000000101100000000000000000000000000001010100000000000000000000000000010100000000000000000000000000000100010000000000000000000000000001000000000000000000000000000000001111 /
b0101 2
b0110 1
b0000000000000000000000000001100000000000000000000000000000011000000000000000000000000000000101110000000000000000000000000001011000000000000000000000000000010101000000000000000000000000000101000000000000000000000000000001000100000000000000000000000000010000 .
#240000
b00000000000000000000000000000101 '
b00000000000000000000000000011001 #
b00000000000000000000000000011001 *
0!
0(
b0000000000000000000000000001100100000000000000000000000000011000000000000000000000000000000101110000000000000000000000000001011000000000000000000000000000010101000000000000000000000000000101000000000000000000000000000001000100000000000000000000000000010000 .
#245000
1!
1(
b0000000000000000000000000001100100000000000000000000000000011000000000000000000000000000000101110000000000000000000000000001011000000000000000000000000000010101000000000000000000000000000101000000000000000000000000000001000100000000000000000000000000010000 /
b0110 2
b0111 1
b0000000000000000000000000001100100000000000000000000000000011001000000000000000000000000000110000000000000000000000000000001011100000000000000000000000000010110000000000000000000000000000101010000000000000000000000000001010000000000000000000000000000010001 .
#250000
b00000000000000000000000000000110 '
b00000000000000000000000000011010 #
b00000000000000000000000000011010 *
0!
0(
b0000000000000000000000000001101000000000000000000000000000011001000000000000000000000000000110000000000000000000000000000001011100000000000000000000000000010110000000000000000000000000000101010000000000000000000000000001010000000000000000000000000000010001 .
#255000
1!
1(
b0000000000000000000000000001101000000000000000000000000000011001000000000000000000000000000110000000000000000000000000000001011100000000000000000000000000010110000000000000000000000000000101010000000000000000000000000001010000000000000000000000000000010001 /
b0111 2
b0000 1
b0000000000000000000000000001101000000000000000000000000000011010000000000000000000000000000110010000000000000000000000000001100000000000000000000000000000010111000000000000000000000000000101100000000000000000000000000001010100000000000000000000000000010100 .
#260000
b00000000000000000000000000000111 '
b00000000000000000000000000011011 #
b00000000000000000000000000011011 *
0!
0(
b0000000000000000000000000001101100000000000000000000000000011010000000000000000000000000000110010000000000000000000000000001100000000000000000000000000000010111000000000000000000000000000101100000000000000000000000000001010100000000000000000000000000010100 .
#265000
1!
1(
b0000000000000000000000000001101100000000000000000000000000011010000000000000000000000000000110010000000000000000000000000001100000000000000000000000000000010111000000000000000000000000000101100000000000000000000000000001010100000000000000000000000000010100 /
b0000 2
b0000000000000000000000000001101100000000000000000000000000011010000000000000000000000000000110010000000000000000000000000001100000000000000000000000000000010111000000000000000000000000000101100000000000000000000000000001010100000000000000000000000000010100 0
b0000000000000000000000000001101100000000000000000000000000011010000000000000000000000000000110010000000000000000000000000001100000000000000000000000000000010111000000000000000000000000000101100000000000000000000000000001010100000000000000000000000000010100 ,
b0000000000000000000000000001101100000000000000000000000000011010000000000000000000000000000110010000000000000000000000000001100000000000000000000000000000010111000000000000000000000000000101100000000000000000000000000001010100000000000000000000000000010100 %
13
1-
1&
b0001 1
b0000000000000000000000000001101100000000000000000000000000011011000000000000000000000000000110100000000000000000000000000001100100000000000000000000000000011000000000000000000000000000000101110000000000000000000000000001011000000000000000000000000000010101 .
#270000
b00000000000000000000000000001000 '
0$
0+
0!
0(
b0000 1
b0000000000000000000000000001101100000000000000000000000000011010000000000000000000000000000110010000000000000000000000000001100000000000000000000000000000010111000000000000000000000000000101100000000000000000000000000001010100000000000000000000000000010100 .
#275000
1!
1(
03
0-
0&
#280000
0!
0(
#285000
1!
1(
#290000
0!
0(
#295000
1!
1(
#300000
0!
0(
#305000
1!
1(
#310000
0!
0(
#315000
1!
1(
#320000
0!
0(
#325000
1!
1(
#330000
0!
0(
#335000
1!
1(
#340000
0!
0(
#345000
1!
1(
#350000
0!
0(
#355000
1!
1(
#360000
0!
0(
#365000
1!
1(
#370000
1$
1+
b00000000000000000000000000000000 '
b00000000000000000000000000011110 #
b00000000000000000000000000011110 *
0!
0(
b0001 1
b0000000000000000000000000001111000000000000000000000000000011011000000000000000000000000000110100000000000000000000000000001100100000000000000000000000000011000000000000000000000000000000101110000000000000000000000000001011000000000000000000000000000010101 .
#375000
1!
1(
b0000000000000000000000000001111000000000000000000000000000011011000000000000000000000000000110100000000000000000000000000001100100000000000000000000000000011000000000000000000000000000000101110000000000000000000000000001011000000000000000000000000000010101 /
b0001 2
b0010 1
b0000000000000000000000000001111000000000000000000000000000011110000000000000000000000000000110110000000000000000000000000001101000000000000000000000000000011001000000000000000000000000000110000000000000000000000000000001011100000000000000000000000000010110 .
#380000
b00000000000000000000000000000001 '
b00000000000000000000000000011111 #
b00000000000000000000000000011111 *
0!
0(
b0000000000000000000000000001111100000000000000000000000000011110000000000000000000000000000110110000000000000000000000000001101000000000000000000000000000011001000000000000000000000000000110000000000000000000000000000001011100000000000000000000000000010110 .
#385000
1!
1(
b0000000000000000000000000001111100000000000000000000000000011110000000000000000000000000000110110000000000000000000000000001101000000000000000000000000000011001000000000000000000000000000110000000000000000000000000000001011100000000000000000000000000010110 /
b0010 2
b0011 1
b0000000000000000000000000001111100000000000000000000000000011111000000000000000000000000000111100000000000000000000000000001101100000000000000000000000000011010000000000000000000000000000110010000000000000000000000000001100000000000000000000000000000010111 .
#390000
b00000000000000000000000000000010 '
b00000000000000000000000000100000 #
b00000000000000000000000000100000 *
0!
0(
b0000000000000000000000000010000000000000000000000000000000011111000000000000000000000000000111100000000000000000000000000001101100000000000000000000000000011010000000000000000000000000000110010000000000000000000000000001100000000000000000000000000000010111 .
#395000
1!
1(
b0000000000000000000000000010000000000000000000000000000000011111000000000000000000000000000111100000000000000000000000000001101100000000000000000000000000011010000000000000000000000000000110010000000000000000000000000001100000000000000000000000000000010111 /
b0011 2
b0100 1
b0000000000000000000000000010000000000000000000000000000000100000000000000000000000000000000111110000000000000000000000000001111000000000000000000000000000011011000000000000000000000000000110100000000000000000000000000001100100000000000000000000000000011000 .
#400000
b00000000000000000000000000000011 '
b00000000000000000000000000100001 #
b00000000000000000000000000100001 *
0!
0(
b0000000000000000000000000010000100000000000000000000000000100000000000000000000000000000000111110000000000000000000000000001111000000000000000000000000000011011000000000000000000000000000110100000000000000000000000000001100100000000000000000000000000011000 .
#405000
1!
1(
b0000000000000000000000000010000100000000000000000000000000100000000000000000000000000000000111110000000000000000000000000001111000000000000000000000000000011011000000000000000000000000000110100000000000000000000000000001100100000000000000000000000000011000 /
b0100 2
b0101 1
b0000000000000000000000000010000100000000000000000000000000100001000000000000000000000000001000000000000000000000000000000001111100000000000000000000000000011110000000000000000000000000000110110000000000000000000000000001101000000000000000000000000000011001 .
#410000
b00000000000000000000000000000100 '
b00000000000000000000000000100010 #
b00000000000000000000000000100010 *
0!
0(
b0000000000000000000000000010001000000000000000000000000000100001000000000000000000000000001000000000000000000000000000000001111100000000000000000000000000011110000000000000000000000000000110110000000000000000000000000001101000000000000000000000000000011001 .
#415000
1!
1(
b0000000000000000000000000010001000000000000000000000000000100001000000000000000000000000001000000000000000000000000000000001111100000000000000000000000000011110000000000000000000000000000110110000000000000000000000000001101000000000000000000000000000011001 /
b0101 2
b0110 1
b0000000000000000000000000010001000000000000000000000000000100010000000000000000000000000001000010000000000000000000000000010000000000000000000000000000000011111000000000000000000000000000111100000000000000000000000000001101100000000000000000000000000011010 .
#420000
b00000000000000000000000000000101 '
b00000000000000000000000000100011 #
b00000000000000000000000000100011 *
0!
0(
b0000000000000000000000000010001100000000000000000000000000100010000000000000000000000000001000010000000000000000000000000010000000000000000000000000000000011111000000000000000000000000000111100000000000000000000000000001101100000000000000000000000000011010 .
#425000
1!
1(
b0000000000000000000000000010001100000000000000000000000000100010000000000000000000000000001000010000000000000000000000000010000000000000000000000000000000011111000000000000000000000000000111100000000000000000000000000001101100000000000000000000000000011010 /
b0110 2
b0111 1
b0000000000000000000000000010001100000000000000000000000000100011000000000000000000000000001000100000000000000000000000000010000100000000000000000000000000100000000000000000000000000000000111110000000000000000000000000001111000000000000000000000000000011011 .
#430000
b00000000000000000000000000000110 '
b00000000000000000000000000100100 #
b00000000000000000000000000100100 *
0!
0(
b0000000000000000000000000010010000000000000000000000000000100011000000000000000000000000001000100000000000000000000000000010000100000000000000000000000000100000000000000000000000000000000111110000000000000000000000000001111000000000000000000000000000011011 .
#435000
1!
1(
b0000000000000000000000000010010000000000000000000000000000100011000000000000000000000000001000100000000000000000000000000010000100000000000000000000000000100000000000000000000000000000000111110000000000000000000000000001111000000000000000000000000000011011 /
b0111 2
b0000 1
b0000000000000000000000000010010000000000000000000000000000100100000000000000000000000000001000110000000000000000000000000010001000000000000000000000000000100001000000000000000000000000001000000000000000000000000000000001111100000000000000000000000000011110 .
#440000
b00000000000000000000000000000111 '
b00000000000000000000000000100101 #
b00000000000000000000000000100101 *
0!
0(
b0000000000000000000000000010010100000000000000000000000000100100000000000000000000000000001000110000000000000000000000000010001000000000000000000000000000100001000000000000000000000000001000000000000000000000000000000001111100000000000000000000000000011110 .
#445000
1!
1(
b0000000000000000000000000010010100000000000000000000000000100100000000000000000000000000001000110000000000000000000000000010001000000000000000000000000000100001000000000000000000000000001000000000000000000000000000000001111100000000000000000000000000011110 /
b0000 2
b0000000000000000000000000010010100000000000000000000000000100100000000000000000000000000001000110000000000000000000000000010001000000000000000000000000000100001000000000000000000000000001000000000000000000000000000000001111100000000000000000000000000011110 0
b0000000000000000000000000010010100000000000000000000000000100100000000000000000000000000001000110000000000000000000000000010001000000000000000000000000000100001000000000000000000000000001000000000000000000000000000000001111100000000000000000000000000011110 ,
b0000000000000000000000000010010100000000000000000000000000100100000000000000000000000000001000110000000000000000000000000010001000000000000000000000000000100001000000000000000000000000001000000000000000000000000000000001111100000000000000000000000000011110 %
13
1-
1&
b0001 1
b0000000000000000000000000010010100000000000000000000000000100101000000000000000000000000001001000000000000000000000000000010001100000000000000000000000000100010000000000000000000000000001000010000000000000000000000000010000000000000000000000000000000011111 .
#450000
b00000000000000000000000000001000 '
0!
0(
#455000
1!
1(
b0000000000000000000000000010010100000000000000000000000000100101000000000000000000000000001001000000000000000000000000000010001100000000000000000000000000100010000000000000000000000000001000010000000000000000000000000010000000000000000000000000000000011111 /
b0001 2
03
0-
0&
b0010 1
b0000000000000000000000000010010100000000000000000000000000100101000000000000000000000000001001010000000000000000000000000010010000000000000000000000000000100011000000000000000000000000001000100000000000000000000000000010000100000000000000000000000000100000 .
#460000
0!
0(
#465000
1!
1(
b0000000000000000000000000010010100000000000000000000000000100101000000000000000000000000001001010000000000000000000000000010010000000000000000000000000000100011000000000000000000000000001000100000000000000000000000000010000100000000000000000000000000100000 /
b0010 2
b0011 1
b0000000000000000000000000010010100000000000000000000000000100101000000000000000000000000001001010000000000000000000000000010010100000000000000000000000000100100000000000000000000000000001000110000000000000000000000000010001000000000000000000000000000100001 .
#470000
0!
0(
#475000
1!
1(
b0000000000000000000000000010010100000000000000000000000000100101000000000000000000000000001001010000000000000000000000000010010100000000000000000000000000100100000000000000000000000000001000110000000000000000000000000010001000000000000000000000000000100001 /
b0011 2
b0100 1
b0000000000000000000000000010010100000000000000000000000000100101000000000000000000000000001001010000000000000000000000000010010100000000000000000000000000100101000000000000000000000000001001000000000000000000000000000010001100000000000000000000000000100010 .
#480000
0!
0(
#485000
1!
1(
b0000000000000000000000000010010100000000000000000000000000100101000000000000000000000000001001010000000000000000000000000010010100000000000000000000000000100101000000000000000000000000001001000000000000000000000000000010001100000000000000000000000000100010 /
b0100 2
b0101 1
b0000000000000000000000000010010100000000000000000000000000100101000000000000000000000000001001010000000000000000000000000010010100000000000000000000000000100101000000000000000000000000001001010000000000000000000000000010010000000000000000000000000000100011 .
#490000
0!
0(
#495000
1!
1(
b0000000000000000000000000010010100000000000000000000000000100101000000000000000000000000001001010000000000000000000000000010010100000000000000000000000000100101000000000000000000000000001001010000000000000000000000000010010000000000000000000000000000100011 /
b0101 2
b0110 1
b0000000000000000000000000010010100000000000000000000000000100101000000000000000000000000001001010000000000000000000000000010010100000000000000000000000000100101000000000000000000000000001001010000000000000000000000000010010100000000000000000000000000100100 .
#500000
0!
0(
#505000
1!
1(
b0000000000000000000000000010010100000000000000000000000000100101000000000000000000000000001001010000000000000000000000000010010100000000000000000000000000100101000000000000000000000000001001010000000000000000000000000010010100000000000000000000000000100100 /
b0110 2
b0111 1
b0000000000000000000000000010010100000000000000000000000000100101000000000000000000000000001001010000000000000000000000000010010100000000000000000000000000100101000000000000000000000000001001010000000000000000000000000010010100000000000000000000000000100101 .
#510000
0!
0(
#515000
1!
1(
b0000000000000000000000000010010100000000000000000000000000100101000000000000000000000000001001010000000000000000000000000010010100000000000000000000000000100101000000000000000000000000001001010000000000000000000000000010010100000000000000000000000000100101 /
b0111 2
b0000 1
#520000
0!
0(
