testbench/counter_tb.sv
`timescale 1ns/1ps
module counter_tb();
    logic   clk,rst_n,cnt_en;
    logic   [4:0] out;
    counter(
        .cnt_clk(clk)        ,
        .cnt_rst_n(rst_n)    ,
        .cnt_en(cnt_en)      ,
        .cnt_o(out)
    );
    initial begin
        
        forever #5 clk = ~clk;
    end

    initial begin
        $dumpfile("./out/tb_counter.vcd");
        $dumpvars(0, counter_tb);
    end

    initial begin
        rst_n=0;
        #10;
        rst_n=1;
        cnt_en=1;
        #200;
        rst_n=0;
        cnt_en=1;
        #200;
        rst_n=1;
        cnt_en=0;
        #200
        rst_n=0;
        cnt_en=0;
        $finish;
    end

endmodule

out/tb_counter.vcd
$date
	Sun May  7 11:36:38 2023
$end

$version
	Synopsys VCS version S-2021.09_Full64
$end

$timescale
	1ps
$end

$comment Csum: 1 86ccb2bd817ce181 $end


$scope module counter_tb $end
$var reg 1 ! clk $end
$var reg 1 " rst_n $end
$var reg 1 # cnt_en $end
$var reg 5 $ out [4:0] $end

$scope module counter $end
$var wire 1 % cnt_clk $end
$var wire 1 & cnt_rst_n $end
$var wire 1 ' cnt_en $end
$var wire 5 ( cnt_o [4:0] $end
$var reg 5 ) counter [4:0] $end
$upscope $end

$upscope $end

$enddefinitions $end

#0
$dumpvars
0!
x#
0&
x'
0"
bxxxxx (
bxxxxx )
bxxxxx $
0%
$end
#5000
1!
1%
b00000 )
b00000 (
b00000 $
#10000
1"
1&
1#
1'
0!
0%
#15000
1!
1%
b00001 )
b00001 (
b00001 $
#20000
0!
0%
#25000
1!
1%
b00010 )
b00010 (
b00010 $
#30000
0!
0%
#35000
1!
1%
b00011 )
b00011 (
b00011 $
#40000
0!
0%
#45000
1!
1%
b00100 )
b00100 (
b00100 $
#50000
0!
0%
#55000
1!
1%
b00101 )
b00101 (
b00101 $
#60000
0!
0%
#65000
1!
1%
b00110 )
b00110 (
b00110 $
#70000
0!
0%
#75000
1!
1%
b00111 )
b00111 (
b00111 $
#80000
0!
0%
#85000
1!
1%
b01000 )
b01000 (
b01000 $
#90000
0!
0%
#95000
1!
1%
b01001 )
b01001 (
b01001 $
#100000
0!
0%
#105000
1!
1%
b01010 )
b01010 (
b01010 $
#110000
0!
0%
#115000
1!
1%
b01011 )
b01011 (
b01011 $
#120000
0!
0%
#125000
1!
1%
b01100 )
b01100 (
b01100 $
#130000
0!
0%
#135000
1!
1%
b01101 )
b01101 (
b01101 $
#140000
0!
0%
#145000
1!
1%
b01110 )
b01110 (
b01110 $
#150000
0!
0%
#155000
1!
1%
b01111 )
b01111 (
b01111 $
#160000
0!
0%
#165000
1!
1%
b10000 )
b10000 (
b10000 $
#170000
0!
0%
#175000
1!
1%
b10001 )
b10001 (
b10001 $
#180000
0!
0%
#185000
1!
1%
b10010 )
b10010 (
b10010 $
#190000
0!
0%
#195000
1!
1%
b10011 )
b10011 (
b10011 $
#200000
0!
0%
#205000
1!
1%
b10100 )
b10100 (
b10100 $
#210000
0"
0&
0!
0%
#215000
1!
1%
b00000 )
b00000 (
b00000 $
#220000
0!
0%
#225000
1!
1%
#230000
0!
0%
#235000
1!
1%
#240000
0!
0%
#245000
1!
1%
#250000
0!
0%
#255000
1!
1%
#260000
0!
0%
#265000
1!
1%
#270000
0!
0%
#275000
1!
1%
#280000
0!
0%
#285000
1!
1%
#290000
0!
0%
#295000
1!
1%
#300000
0!
0%
#305000
1!
1%
#310000
0!
0%
#315000
1!
1%
#320000
0!
0%
#325000
1!
1%
#330000
0!
0%
#335000
1!
1%
#340000
0!
0%
#345000
1!
1%
#350000
0!
0%
#355000
1!
1%
#360000
0!
0%
#365000
1!
1%
#370000
0!
0%
#375000
1!
1%
#380000
0!
0%
#385000
1!
1%
#390000
0!
0%
#395000
1!
1%
#400000
0!
0%
#405000
1!
1%
#410000
1"
1&
0#
0'
0!
0%
#415000
1!
1%
#420000
0!
0%
#425000
1!
1%
#430000
0!
0%
#435000
1!
1%
#440000
0!
0%
#445000
1!
1%
#450000
0!
0%
#455000
1!
1%
#460000
0!
0%
#465000
1!
1%
#470000
0!
0%
#475000
1!
1%
#480000
0!
0%
#485000
1!
1%
#490000
0!
0%
#495000
1!
1%
#500000
0!
0%
#505000
1!
1%
#510000
0!
0%
#515000
1!
1%
#520000
0!
0%
#525000
1!
1%
#530000
0!
0%
#535000
1!
1%
#540000
0!
0%
#545000
1!
1%
#550000
0!
0%
#555000
1!
1%
#560000
0!
0%
#565000
1!
1%
#570000
0!
0%
#575000
1!
1%
#580000
0!
0%
#585000
1!
1%
#590000
0!
0%
#595000
1!
1%
#600000
0!
0%
#605000
1!
1%
#610000
0"
0&
